Workbook

Sheet PL
D1: CERTIFICADO DE PAGO | AL1: Fecha: | AM1: 46132
AL2: 1
D3: CLIENTE: | E3: EMBOL S.A. / GERENCIA DE OPERACIONES E INNOVACION TECNOLOGICA | W3: PERIODO: | Y3: 46113
D5: SERVICIO: | E5: SERVICIO DE SUPERVISION DE PROYECTOS | W5: DIAS LABORABLES: | AA5: 22
D7: ORDEN DE COMPRA: | W7: MONEDA: | Y7: Bolivianos
AL8: CERTIFICADO
A10: PLANILLA DE PERSONAL
A12: ITEM | B12: NOMBRE | C12: CARGO | D12: FECHA DE INICIO | E12: HABER BASICO | F12: DIAS | AK12: TOTAL DIAS | AL12: HABER GANADO | AM12: FACTURADO
F13: 1 | G13: 2 | H13: 3 | I13: 4 | J13: 5 | K13: 6 | L13: 7 | M13: 8 | N13: 9 | O13: 10 | P13: 11 | Q13: 12 | R13: 13 | S13: 14 | T13: 15 | U13: 16 | V13: 17 | W13: 18 | X13: 19 | Y13: 20 | Z13: 21 | AA13: 22 | AB13: 23 | AC13: 24 | AD13: 25 | AE13: 26 | AF13: 27 | AG13: 28 | AH13: 29 | AI13: 30
A14: 1 | B14: RAMIRO ARMANDO SUAREZ RIBERO | C14: Project Manager Central | D14: 46113 | E14: 9500 | F14: =+IF('1'!F10>1,"SI","NO") -> SI | G14: =+IF('1'!F11>1,"SI","NO") -> SI | H14: =+IF('1'!F12>1,"SI","NO") -> NO | I14: =+IF('1'!F13>1,"SI","NO") -> NO | J14: =+IF('1'!F14>1,"SI","NO") -> NO | K14: =+IF('1'!F15>1,"SI","NO") -> SI | L14: =+IF('1'!F16>1,"SI","NO") -> SI | M14: =+IF('1'!F17>1,"SI","NO") -> SI | N14: =+IF('1'!F18>1,"SI","NO") -> SI | O14: =+IF('1'!F19>1,"SI","NO") -> SI | P14: =+IF('1'!F20>1,"SI","NO") -> NO | Q14: =+IF('1'!F21>1,"SI","NO") -> NO | R14: =+IF('1'!F22>1,"SI","NO") -> SI | S14: =+IF('1'!F23>1,"SI","NO") -> SI | T14: =+IF('1'!F24>1,"SI","NO") -> SI | U14: =+IF('1'!F25>1,"SI","NO") -> SI | V14: =+IF('1'!F26>1,"SI","NO") -> SI | W14: =+IF('1'!F27>1,"SI","NO") -> SI | X14: =+IF('1'!F28>1,"SI","NO") -> NO | Y14: =+IF('1'!F29>1,"SI","NO") -> SI | Z14: =+IF('1'!F30>1,"SI","NO") -> NO | AA14: =+IF('1'!F31>1,"SI","NO") -> NO | AB14: =+IF('1'!F32>1,"SI","NO") -> NO | AC14: =+IF('1'!F33>1,"SI","NO") -> NO | AD14: =+IF('1'!F34>1,"SI","NO") -> NO | AE14: =+IF('1'!F35>1,"SI","NO") -> NO | AF14: =+IF('1'!F36>1,"SI","NO") -> NO | AG14: =+IF('1'!F37>1,"SI","NO") -> NO | AH14: =+IF('1'!F38>1,"SI","NO") -> NO | AI14: =+IF('1'!F39>1,"SI","NO") -> NO | AK14: =+COUNTIF(F14:AJ14,"SI") -> 14 | AL14: =+AK14/$AA$5*E14 -> 6045.4545 | AM14: =+AL14/0.461310893326238 -> 13104.946
A15: 2 | B15: ERICKA YOSELIN FLORES VACA | C15: Project Manager Regional SCZ | D15: 46118 | E15: 8000 | F15: =+IF('2'!F10>1,"SI","NO") -> NO | G15: =+IF('2'!F11>1,"SI","NO") -> NO | H15: =+IF('2'!F12>1,"SI","NO") -> NO | I15: =+IF('2'!F13>1,"SI","NO") -> NO | J15: =+IF('2'!F14>1,"SI","NO") -> NO | K15: =+IF('2'!F15>1,"SI","NO") -> SI | L15: =+IF('2'!F16>1,"SI","NO") -> SI | M15: =+IF('2'!F17>1,"SI","NO") -> SI | N15: =+IF('2'!F18>1,"SI","NO") -> SI | O15: =+IF('2'!F19>1,"SI","NO") -> SI | P15: =+IF('2'!F20>1,"SI","NO") -> NO | Q15: =+IF('2'!F21>1,"SI","NO") -> NO | R15: =+IF('2'!F22>1,"SI","NO") -> SI | S15: =+IF('2'!F23>1,"SI","NO") -> SI | T15: =+IF('2'!F24>1,"SI","NO") -> SI | U15: =+IF('2'!F25>1,"SI","NO") -> SI | V15: =+IF('2'!F26>1,"SI","NO") -> SI | W15: =+IF('2'!F27>1,"SI","NO") -> NO | X15: =+IF('2'!F28>1,"SI","NO") -> NO | Y15: =+IF('2'!F29>1,"SI","NO") -> SI | Z15: =+IF('2'!F30>1,"SI","NO") -> NO | AA15: =+IF('2'!F31>1,"SI","NO") -> NO | AB15: =+IF('2'!F32>1,"SI","NO") -> NO | AC15: =+IF('2'!F33>1,"SI","NO") -> NO | AD15: =+IF('2'!F34>1,"SI","NO") -> NO | AE15: =+IF('2'!F35>1,"SI","NO") -> NO | AF15: =+IF('2'!F36>1,"SI","NO") -> NO | AG15: =+IF('2'!F37>1,"SI","NO") -> NO | AH15: =+IF('2'!F38>1,"SI","NO") -> NO | AI15: =+IF('2'!F39>1,"SI","NO") -> NO | AK15: =+COUNTIF(F15:AJ15,"SI") -> 11 | AL15: =+AK15/$AA$5*E15 -> 4000 | AM15: =+AL15/0.461310893326238 -> 8670.942
A16: 3 | B16: CESAR JOSÉ MOYA VARGAS | C16: Project Manager Regional LPZ | D16: 46118 | E16: 8000 | F16: =+IF('3'!F10>1,"SI","NO") -> NO | G16: =+IF('3'!F11>1,"SI","NO") -> NO | H16: =+IF('3'!F12>1,"SI","NO") -> NO | I16: =+IF('3'!F13>1,"SI","NO") -> NO | J16: =+IF('3'!F14>1,"SI","NO") -> NO | K16: =+IF('3'!F15>1,"SI","NO") -> SI | L16: =+IF('3'!F16>1,"SI","NO") -> SI | M16: =+IF('3'!F17>1,"SI","NO") -> SI | N16: =+IF('3'!F18>1,"SI","NO") -> SI | O16: =+IF('3'!F19>1,"SI","NO") -> SI | P16: =+IF('3'!F20>1,"SI","NO") -> NO | Q16: =+IF('3'!F21>1,"SI","NO") -> NO | R16: =+IF('3'!F22>1,"SI","NO") -> SI | S16: =+IF('3'!F23>1,"SI","NO") -> SI | T16: =+IF('3'!F24>1,"SI","NO") -> SI | U16: =+IF('3'!F25>1,"SI","NO") -> SI | V16: =+IF('3'!F26>1,"SI","NO") -> SI | W16: =+IF('3'!F27>1,"SI","NO") -> NO | X16: =+IF('3'!F28>1,"SI","NO") -> NO | Y16: =+IF('3'!F29>1,"SI","NO") -> SI | Z16: =+IF('3'!F30>1,"SI","NO") -> NO | AA16: =+IF('3'!F31>1,"SI","NO") -> NO | AB16: =+IF('3'!F32>1,"SI","NO") -> NO | AC16: =+IF('3'!F33>1,"SI","NO") -> NO | AD16: =+IF('3'!F34>1,"SI","NO") -> NO | AE16: =+IF('3'!F35>1,"SI","NO") -> NO | AF16: =+IF('3'!F36>1,"SI","NO") -> NO | AG16: =+IF('3'!F37>1,"SI","NO") -> NO | AH16: =+IF('3'!F38>1,"SI","NO") -> NO | AI16: =+IF('3'!F39>1,"SI","NO") -> NO | AK16: =+COUNTIF(F16:AJ16,"SI") -> 11 | AL16: =+AK16/$AA$5*E16 -> 4000 | AM16: =+AL16/0.461310893326238 -> 8670.942
A17: 4 | B17: OSCAR ROLANDO MENDEZ ROCA FARELL | C17: Project Manager Regional CBA | D17: 46126 | E17: 8000 | F17: =+IF('4'!F10>1,"SI","NO") -> NO | G17: =+IF('4'!F11>1,"SI","NO") -> NO | H17: =+IF('4'!F12>1,"SI","NO") -> NO | I17: =+IF('4'!F13>1,"SI","NO") -> NO | J17: =+IF('4'!F14>1,"SI","NO") -> NO | K17: =+IF('4'!F15>1,"SI","NO") -> NO | L17: =+IF('4'!F16>1,"SI","NO") -> NO | M17: =+IF('4'!F17>1,"SI","NO") -> NO | N17: =+IF('4'!F18>1,"SI","NO") -> NO | O17: =+IF('4'!F19>1,"SI","NO") -> NO | P17: =+IF('4'!F20>1,"SI","NO") -> NO | Q17: =+IF('4'!F21>1,"SI","NO") -> NO | R17: =+IF('4'!F22>1,"SI","NO") -> NO | S17: =+IF('4'!F23>1,"SI","NO") -> SI | T17: =+IF('4'!F24>1,"SI","NO") -> SI | U17: =+IF('4'!F25>1,"SI","NO") -> SI | V17: =+IF('4'!F26>1,"SI","NO") -> SI | W17: =+IF('4'!F27>1,"SI","NO") -> SI | X17: =+IF('4'!F28>1,"SI","NO") -> NO | Y17: =+IF('4'!F29>1,"SI","NO") -> SI | Z17: =+IF('4'!F30>1,"SI","NO") -> NO | AA17: =+IF('4'!F31>1,"SI","NO") -> NO | AB17: =+IF('4'!F32>1,"SI","NO") -> NO | AC17: =+IF('4'!F33>1,"SI","NO") -> NO | AD17: =+IF('4'!F34>1,"SI","NO") -> NO | AE17: =+IF('4'!F35>1,"SI","NO") -> NO | AF17: =+IF('4'!F36>1,"SI","NO") -> NO | AG17: =+IF('4'!F37>1,"SI","NO") -> NO | AH17: =+IF('4'!F38>1,"SI","NO") -> NO | AI17: =+IF('4'!F39>1,"SI","NO") -> NO | AK17: =+COUNTIF(F17:AJ17,"SI") -> 6 | AL17: =+AK17/$AA$5*E17 -> 2181.8182 | AM17: =+AL17/0.461310893326238 -> 4729.6047
A18: 5 | B18: JORGE LUIS ROJAS DÁVILA | C18: Supervisor Civil Regional SCZ | D18: 46113 | E18: 9165 | F18: =+IF('5'!F10>1,"SI","NO") -> SI | G18: =+IF('5'!F11>1,"SI","NO") -> NO | H18: =+IF('5'!F12>1,"SI","NO") -> NO | I18: =+IF('5'!F13>1,"SI","NO") -> NO | J18: =+IF('5'!F14>1,"SI","NO") -> NO | K18: =+IF('5'!F15>1,"SI","NO") -> SI | L18: =+IF('5'!F16>1,"SI","NO") -> SI | M18: =+IF('5'!F17>1,"SI","NO") -> SI | N18: =+IF('5'!F18>1,"SI","NO") -> SI | O18: =+IF('5'!F19>1,"SI","NO") -> SI | P18: =+IF('5'!F20>1,"SI","NO") -> NO | Q18: =+IF('5'!F21>1,"SI","NO") -> NO | R18: =+IF('5'!F22>1,"SI","NO") -> SI | S18: =+IF('5'!F23>1,"SI","NO") -> SI | T18: =+IF('5'!F24>1,"SI","NO") -> SI | U18: =+IF('5'!F25>1,"SI","NO") -> SI | V18: =+IF('5'!F26>1,"SI","NO") -> SI | W18: =+IF('5'!F27>1,"SI","NO") -> NO | X18: =+IF('5'!F28>1,"SI","NO") -> NO | Y18: =+IF('5'!F29>1,"SI","NO") -> SI | Z18: =+IF('5'!F30>1,"SI","NO") -> NO | AA18: =+IF('5'!F31>1,"SI","NO") -> NO | AB18: =+IF('5'!F32>1,"SI","NO") -> NO | AC18: =+IF('5'!F33>1,"SI","NO") -> NO | AD18: =+IF('5'!F34>1,"SI","NO") -> NO | AE18: =+IF('5'!F35>1,"SI","NO") -> NO | AF18: =+IF('5'!F36>1,"SI","NO") -> NO | AG18: =+IF('5'!F37>1,"SI","NO") -> NO | AH18: =+IF('5'!F38>1,"SI","NO") -> NO | AI18: =+IF('5'!F39>1,"SI","NO") -> NO | AK18: =+COUNTIF(F18:AJ18,"SI") -> 12 | AL18: =+AK18/$AA$5*E18 -> 4999.0909 | AM18: =+AL18/0.461310893326238 -> 10836.707
A19: 6 | B19: OSCAR FABIAN QUIROGA TAMAYO | C19: Supervisor Civil Regional CBA | D19: 46119 | E19: 8485 | F19: =+IF('6'!F10>1,"SI","NO") -> SI | G19: =+IF('6'!F11>1,"SI","NO") -> SI | H19: =+IF('6'!F12>1,"SI","NO") -> NO | I19: =+IF('6'!F13>1,"SI","NO") -> NO | J19: =+IF('6'!F14>1,"SI","NO") -> NO | K19: =+IF('6'!F15>1,"SI","NO") -> SI | L19: =+IF('6'!F16>1,"SI","NO") -> SI | M19: =+IF('6'!F17>1,"SI","NO") -> SI | N19: =+IF('6'!F18>1,"SI","NO") -> SI | O19: =+IF('6'!F19>1,"SI","NO") -> SI | P19: =+IF('6'!F20>1,"SI","NO") -> NO | Q19: =+IF('6'!F21>1,"SI","NO") -> NO | R19: =+IF('6'!F22>1,"SI","NO") -> SI | S19: =+IF('6'!F23>1,"SI","NO") -> SI | T19: =+IF('6'!F24>1,"SI","NO") -> SI | U19: =+IF('6'!F25>1,"SI","NO") -> SI | V19: =+IF('6'!F26>1,"SI","NO") -> SI | W19: =+IF('6'!F27>1,"SI","NO") -> SI | X19: =+IF('6'!F28>1,"SI","NO") -> NO | Y19: =+IF('6'!F29>1,"SI","NO") -> SI | Z19: =+IF('6'!F30>1,"SI","NO") -> NO | AA19: =+IF('6'!F31>1,"SI","NO") -> NO | AB19: =+IF('6'!F32>1,"SI","NO") -> NO | AC19: =+IF('6'!F33>1,"SI","NO") -> NO | AD19: =+IF('6'!F34>1,"SI","NO") -> NO | AE19: =+IF('6'!F35>1,"SI","NO") -> NO | AF19: =+IF('6'!F36>1,"SI","NO") -> NO | AG19: =+IF('6'!F37>1,"SI","NO") -> NO | AH19: =+IF('6'!F38>1,"SI","NO") -> NO | AI19: =+IF('6'!F39>1,"SI","NO") -> NO | AK19: =+COUNTIF(F19:AJ19,"SI") -> 14 | AL19: =+AK19/$AA$5*E19 -> 5399.5455 | AM19: =+AL19/0.461310893326238 -> 11704.786
A20: 7 | B20: MARTIN EDUARDO VELIZ AREVALO | C20: Supervisor Civil Regional LPZ | D20: 46113 | E20: 8485 | F20: =+IF('7'!F10>1,"SI","NO") -> NO | G20: =+IF('7'!F11>1,"SI","NO") -> NO | H20: =+IF('7'!F12>1,"SI","NO") -> NO | I20: =+IF('7'!F13>1,"SI","NO") -> NO | J20: =+IF('7'!F14>1,"SI","NO") -> NO | K20: =+IF('7'!F15>1,"SI","NO") -> NO | L20: =+IF('7'!F16>1,"SI","NO") -> SI | M20: =+IF('7'!F17>1,"SI","NO") -> SI | N20: =+IF('7'!F18>1,"SI","NO") -> SI | O20: =+IF('7'!F19>1,"SI","NO") -> SI | P20: =+IF('7'!F20>1,"SI","NO") -> NO | Q20: =+IF('7'!F21>1,"SI","NO") -> NO | R20: =+IF('7'!F22>1,"SI","NO") -> SI | S20: =+IF('7'!F23>1,"SI","NO") -> SI | T20: =+IF('7'!F24>1,"SI","NO") -> SI | U20: =+IF('7'!F25>1,"SI","NO") -> SI | V20: =+IF('7'!F26>1,"SI","NO") -> SI | W20: =+IF('7'!F27>1,"SI","NO") -> NO | X20: =+IF('7'!F28>1,"SI","NO") -> NO | Y20: =+IF('7'!F29>1,"SI","NO") -> SI | Z20: =+IF('7'!F30>1,"SI","NO") -> NO | AA20: =+IF('7'!F31>1,"SI","NO") -> NO | AB20: =+IF('7'!F32>1,"SI","NO") -> NO | AC20: =+IF('7'!F33>1,"SI","NO") -> NO | AD20: =+IF('7'!F34>1,"SI","NO") -> NO | AE20: =+IF('7'!F35>1,"SI","NO") -> NO | AF20: =+IF('7'!F36>1,"SI","NO") -> NO | AG20: =+IF('7'!F37>1,"SI","NO") -> NO | AH20: =+IF('7'!F38>1,"SI","NO") -> NO | AI20: =+IF('7'!F39>1,"SI","NO") -> NO | AK20: =+COUNTIF(F20:AJ20,"SI") -> 10 | AL20: =+AK20/$AA$5*E20 -> 3856.8182 | AM20: =+AL20/0.461310893326238 -> 8360.5617
A21: 8 | B21: RAÚL RAIMUNDO PARRAGA ANTEZANA | C21: Supervisor Eléctrico Regional | D21: 46113 | E21: 9165 | F21: =+IF('8'!F10>1,"SI","NO") -> SI | G21: =+IF('8'!F11>1,"SI","NO") -> SI | H21: =+IF('8'!F12>1,"SI","NO") -> NO | I21: =+IF('8'!F13>1,"SI","NO") -> NO | J21: =+IF('8'!F14>1,"SI","NO") -> NO | K21: =+IF('8'!F15>1,"SI","NO") -> SI | L21: =+IF('8'!F16>1,"SI","NO") -> SI | M21: =+IF('8'!F17>1,"SI","NO") -> SI | N21: =+IF('8'!F18>1,"SI","NO") -> SI | O21: =+IF('8'!F19>1,"SI","NO") -> SI | P21: =+IF('8'!F20>1,"SI","NO") -> NO | Q21: =+IF('8'!F21>1,"SI","NO") -> NO | R21: =+IF('8'!F22>1,"SI","NO") -> SI | S21: =+IF('8'!F23>1,"SI","NO") -> NO | T21: =+IF('8'!F24>1,"SI","NO") -> SI | U21: =+IF('8'!F25>1,"SI","NO") -> SI | V21: =+IF('8'!F26>1,"SI","NO") -> SI | W21: =+IF('8'!F27>1,"SI","NO") -> NO | X21: =+IF('8'!F28>1,"SI","NO") -> NO | Y21: =+IF('8'!F29>1,"SI","NO") -> SI | Z21: =+IF('8'!F30>1,"SI","NO") -> NO | AA21: =+IF('8'!F31>1,"SI","NO") -> NO | AB21: =+IF('8'!F32>1,"SI","NO") -> NO | AC21: =+IF('8'!F33>1,"SI","NO") -> NO | AD21: =+IF('8'!F34>1,"SI","NO") -> NO | AE21: =+IF('8'!F35>1,"SI","NO") -> NO | AF21: =+IF('8'!F36>1,"SI","NO") -> NO | AG21: =+IF('8'!F37>1,"SI","NO") -> NO | AH21: =+IF('8'!F38>1,"SI","NO") -> NO | AI21: =+IF('8'!F39>1,"SI","NO") -> NO | AK21: =+COUNTIF(F21:AJ21,"SI") -> 12 | AL21: =+AK21/$AA$5*E21 -> 4999.0909 | AM21: =+AL21/0.461310893326238 -> 10836.707
A22: 9 | B22: ABRAHAM QUENA CABRERA | C22: Supervisor Mecánico Regional | D22: 46113 | E22: 9165 | F22: =+IF('9'!F10>1,"SI","NO") -> SI | G22: =+IF('9'!F11>1,"SI","NO") -> SI | H22: =+IF('9'!F12>1,"SI","NO") -> NO | I22: =+IF('9'!F13>1,"SI","NO") -> NO | J22: =+IF('9'!F14>1,"SI","NO") -> NO | K22: =+IF('9'!F15>1,"SI","NO") -> SI | L22: =+IF('9'!F16>1,"SI","NO") -> SI | M22: =+IF('9'!F17>1,"SI","NO") -> SI | N22: =+IF('9'!F18>1,"SI","NO") -> SI | O22: =+IF('9'!F19>1,"SI","NO") -> SI | P22: =+IF('9'!F20>1,"SI","NO") -> NO | Q22: =+IF('9'!F21>1,"SI","NO") -> NO | R22: =+IF('9'!F22>1,"SI","NO") -> SI | S22: =+IF('9'!F23>1,"SI","NO") -> SI | T22: =+IF('9'!F24>1,"SI","NO") -> SI | U22: =+IF('9'!F25>1,"SI","NO") -> SI | V22: =+IF('9'!F26>1,"SI","NO") -> SI | W22: =+IF('9'!F27>1,"SI","NO") -> NO | X22: =+IF('9'!F28>1,"SI","NO") -> NO | Y22: =+IF('9'!F29>1,"SI","NO") -> SI | Z22: =+IF('9'!F30>1,"SI","NO") -> NO | AA22: =+IF('9'!F31>1,"SI","NO") -> NO | AB22: =+IF('9'!F32>1,"SI","NO") -> NO | AC22: =+IF('9'!F33>1,"SI","NO") -> NO | AD22: =+IF('9'!F34>1,"SI","NO") -> NO | AE22: =+IF('9'!F35>1,"SI","NO") -> NO | AF22: =+IF('9'!F36>1,"SI","NO") -> NO | AG22: =+IF('9'!F37>1,"SI","NO") -> NO | AH22: =+IF('9'!F38>1,"SI","NO") -> NO | AI22: =+IF('9'!F39>1,"SI","NO") -> NO | AK22: =+COUNTIF(F22:AJ22,"SI") -> 13 | AL22: =+AK22/$AA$5*E22 -> 5415.6818 | AM22: =+AL22/0.461310893326238 -> 11739.766
A23: 10 | B23: DAVID ARIEL PEREDO MIRANDA | C23: Supervisor Elt/Mec Regional | D23: 46113 | E23: 16240 | F23: =+IF('10'!F10>1,"SI","NO") -> SI | G23: =+IF('10'!F11>1,"SI","NO") -> SI | H23: =+IF('10'!F12>1,"SI","NO") -> NO | I23: =+IF('10'!F13>1,"SI","NO") -> NO | J23: =+IF('10'!F14>1,"SI","NO") -> NO | K23: =+IF('10'!F15>1,"SI","NO") -> SI | L23: =+IF('10'!F16>1,"SI","NO") -> SI | M23: =+IF('10'!F17>1,"SI","NO") -> SI | N23: =+IF('10'!F18>1,"SI","NO") -> SI | O23: =+IF('10'!F19>1,"SI","NO") -> SI | P23: =+IF('10'!F20>1,"SI","NO") -> NO | Q23: =+IF('10'!F21>1,"SI","NO") -> NO | R23: =+IF('10'!F22>1,"SI","NO") -> SI | S23: =+IF('10'!F23>1,"SI","NO") -> SI | T23: =+IF('10'!F24>1,"SI","NO") -> SI | U23: =+IF('10'!F25>1,"SI","NO") -> SI | V23: =+IF('10'!F26>1,"SI","NO") -> SI | W23: =+IF('10'!F27>1,"SI","NO") -> NO | X23: =+IF('10'!F28>1,"SI","NO") -> NO | Y23: =+IF('10'!F29>1,"SI","NO") -> SI | Z23: =+IF('10'!F30>1,"SI","NO") -> NO | AA23: =+IF('10'!F31>1,"SI","NO") -> NO | AB23: =+IF('10'!F32>1,"SI","NO") -> NO | AC23: =+IF('10'!F33>1,"SI","NO") -> NO | AD23: =+IF('10'!F34>1,"SI","NO") -> NO | AE23: =+IF('10'!F35>1,"SI","NO") -> NO | AF23: =+IF('10'!F36>1,"SI","NO") -> NO | AG23: =+IF('10'!F37>1,"SI","NO") -> NO | AH23: =+IF('10'!F38>1,"SI","NO") -> NO | AI23: =+IF('10'!F39>1,"SI","NO") -> NO | AK23: =+COUNTIF(F23:AJ23,"SI") -> 13 | AL23: =+AK23/$AA$5*E23 -> 9596.3636 | AM23: =+AL23/0.461310893326238 -> 20802.378
A24: 11 | B24: ERIN CALLEJAS VELASQUEZ | C24: Supervisor Elt/Mec Regional | D24: 46113 | E24: 12483 | F24: =+IF('11'!F10>1,"SI","NO") -> SI | G24: =+IF('11'!F11>1,"SI","NO") -> NO | H24: =+IF('11'!F12>1,"SI","NO") -> NO | I24: =+IF('11'!F13>1,"SI","NO") -> NO | J24: =+IF('11'!F14>1,"SI","NO") -> NO | K24: =+IF('11'!F15>1,"SI","NO") -> SI | L24: =+IF('11'!F16>1,"SI","NO") -> SI | M24: =+IF('11'!F17>1,"SI","NO") -> SI | N24: =+IF('11'!F18>1,"SI","NO") -> SI | O24: =+IF('11'!F19>1,"SI","NO") -> SI | P24: =+IF('11'!F20>1,"SI","NO") -> NO | Q24: =+IF('11'!F21>1,"SI","NO") -> NO | R24: =+IF('11'!F22>1,"SI","NO") -> SI | S24: =+IF('11'!F23>1,"SI","NO") -> SI | T24: =+IF('11'!F24>1,"SI","NO") -> SI | U24: =+IF('11'!F25>1,"SI","NO") -> SI | V24: =+IF('11'!F26>1,"SI","NO") -> SI | W24: =+IF('11'!F27>1,"SI","NO") -> NO | X24: =+IF('11'!F28>1,"SI","NO") -> NO | Y24: =+IF('11'!F29>1,"SI","NO") -> SI | Z24: =+IF('11'!F30>1,"SI","NO") -> NO | AA24: =+IF('11'!F31>1,"SI","NO") -> NO | AB24: =+IF('11'!F32>1,"SI","NO") -> NO | AC24: =+IF('11'!F33>1,"SI","NO") -> NO | AD24: =+IF('11'!F34>1,"SI","NO") -> NO | AE24: =+IF('11'!F35>1,"SI","NO") -> NO | AF24: =+IF('11'!F36>1,"SI","NO") -> NO | AG24: =+IF('11'!F37>1,"SI","NO") -> NO | AH24: =+IF('11'!F38>1,"SI","NO") -> NO | AI24: =+IF('11'!F39>1,"SI","NO") -> NO | AK24: =+COUNTIF(F24:AJ24,"SI") -> 12 | AL24: =+AK24/$AA$5*E24 -> 6808.9091 | AM24: =+AL24/0.461310893326238 -> 14759.914
A25: 12 | B25: JOSUÉ CONRRADO FERNÁNDEZ SOTEZ | C25: Encargado de Almacén | D25: 46113 | E25: 3808 | F25: =+IF('12'!F10>1,"SI","NO") -> SI | G25: =+IF('12'!F11>1,"SI","NO") -> SI | H25: =+IF('12'!F12>1,"SI","NO") -> NO | I25: =+IF('12'!F13>1,"SI","NO") -> NO | J25: =+IF('12'!F14>1,"SI","NO") -> NO | K25: =+IF('12'!F15>1,"SI","NO") -> SI | L25: =+IF('12'!F16>1,"SI","NO") -> SI | M25: =+IF('12'!F17>1,"SI","NO") -> SI | N25: =+IF('12'!F18>1,"SI","NO") -> SI | O25: =+IF('12'!F19>1,"SI","NO") -> SI | P25: =+IF('12'!F20>1,"SI","NO") -> SI | Q25: =+IF('12'!F21>1,"SI","NO") -> NO | R25: =+IF('12'!F22>1,"SI","NO") -> SI | S25: =+IF('12'!F23>1,"SI","NO") -> SI | T25: =+IF('12'!F24>1,"SI","NO") -> SI | U25: =+IF('12'!F25>1,"SI","NO") -> SI | V25: =+IF('12'!F26>1,"SI","NO") -> SI | W25: =+IF('12'!F27>1,"SI","NO") -> SI | X25: =+IF('12'!F28>1,"SI","NO") -> NO | Y25: =+IF('12'!F29>1,"SI","NO") -> SI | Z25: =+IF('12'!F30>1,"SI","NO") -> NO | AA25: =+IF('12'!F31>1,"SI","NO") -> NO | AB25: =+IF('12'!F32>1,"SI","NO") -> NO | AC25: =+IF('12'!F33>1,"SI","NO") -> NO | AD25: =+IF('12'!F34>1,"SI","NO") -> NO | AE25: =+IF('12'!F35>1,"SI","NO") -> NO | AF25: =+IF('12'!F36>1,"SI","NO") -> NO | AG25: =+IF('12'!F37>1,"SI","NO") -> NO | AH25: =+IF('12'!F38>1,"SI","NO") -> NO | AI25: =+IF('12'!F39>1,"SI","NO") -> NO | AK25: =+COUNTIF(F25:AJ25,"SI") -> 15 | AL25: =+AK25/$AA$5*E25 -> 2596.3636 | AM25: =+AL25/0.461310893326238 -> 5628.2296
AM26: =SUM(AM14:AM25) -> 129845.48
A28: PASAJES Y VIATICOS | U28: ALQUILER EQUIPOS DE COMPUTACION
A30: ITEM | B30: NOMBRE | C30: DESCRIPCION | D30: FECHA IDA | E30: FECHA REGRESO | F30: DIAS | H30: P.U. (Variable) | K30: CANTIDAD | N30: COSTO TOTAL | P30: FACTURADO | U30: ITEM | W30: DESCRIPCION | AJ30: CANTIDAD | AL30: COSTO TOTAL | AM30: FACTURADO
A32: 1 | N32: =+K32*H32 -> 0 | P32: =+N32*1.25 -> 0 | U32: 1 | W32: Dotación de Equipos de Computación i5/i7 de ÚLTIMA GENERACIÓN con Licencia Software Basico - Contrato anual. | AJ32: 11 | AL32: 785 | AM32: =+AL32*AJ32 -> 8635
A33: 2 | N33: =+K33*H33 -> 0 | P33: =+N33*1.25 -> 0
A34: 3 | N34: =+K34*H34 -> 0 | P34: =+N34*1.25 -> 0 | U34: 2 | W34: Dotación de Equipos de Computación i5/i7 de ÚLTIMA GENERACIÓN con Licencia Software Especializado de diseño - Contrato anual. | AJ34: 0 | AL34: 4857.5 | AM34: =+AL34*AJ34 -> 0
A35: 4 | N35: =+K35*H35 -> 0 | P35: =+N35*1.25 -> 0
A36: 5 | N36: =+F36*H36 -> 0 | P36: =+N36*1.25 -> 0 | AM36: =SUM(AM32:AM35) -> 8635
P37: =SUM(P32:S36) -> 0
A39: PLANILLA DE ALIMENTACION LA PAZ | AL39: Fee Cont | AM39: 1.16
A41: ITEM | B41: NOMBRE | C41: CARGO | D41: FECHA DE INICIO | E41: P.U. CATERING | F41: DIAS | AK41: TOTAL DIAS | AL41: COSTO TOTAL | AM41: FACTURADO
F42: 1 | G42: 2 | H42: 3 | I42: 4 | J42: 5 | K42: 6 | L42: 7 | M42: 8 | N42: 9 | O42: 10 | P42: 11 | Q42: 12 | R42: 13 | S42: 14 | T42: 15 | U42: 16 | V42: 17 | W42: 18 | X42: 19 | Y42: 20 | Z42: 21 | AA42: 22 | AB42: 23 | AC42: 24 | AD42: 25 | AE42: 26 | AF42: 27 | AG42: 28 | AH42: 29 | AI42: 30
A43: 3 | B43: CESAR JOSÉ MOYA VARGAS | C43: Project Manager Regional LPZ | D43: 46113 | E43: 25 | F43: =+IF('3'!F10>1,"SI","NO") -> NO | G43: =+IF('3'!F11>1,"SI","NO") -> NO | H43: =+IF('3'!F12>1,"SI","NO") -> NO | I43: =+IF('3'!F13>1,"SI","NO") -> NO | J43: =+IF('3'!F14>1,"SI","NO") -> NO | K43: =+IF('3'!F15>1,"SI","NO") -> SI | L43: =+IF('3'!F16>1,"SI","NO") -> SI | M43: =+IF('3'!F17>1,"SI","NO") -> SI | N43: =+IF('3'!F18>1,"SI","NO") -> SI | O43: =+IF('3'!F19>1,"SI","NO") -> SI | P43: =+IF('3'!F20>1,"SI","NO") -> NO | Q43: =+IF('3'!F21>1,"SI","NO") -> NO | R43: =+IF('3'!F22>1,"SI","NO") -> SI | S43: =+IF('3'!F23>1,"SI","NO") -> SI | T43: =+IF('3'!F24>1,"SI","NO") -> SI | U43: =+IF('3'!F25>1,"SI","NO") -> SI | V43: =+IF('3'!F26>1,"SI","NO") -> SI | W43: =+IF('3'!F27>1,"SI","NO") -> NO | X43: =+IF('3'!F28>1,"SI","NO") -> NO | Y43: =+IF('3'!F29>1,"SI","NO") -> SI | Z43: =+IF('3'!F30>1,"SI","NO") -> NO | AA43: =+IF('3'!F31>1,"SI","NO") -> NO | AB43: =+IF('3'!F32>1,"SI","NO") -> NO | AC43: =+IF('3'!F33>1,"SI","NO") -> NO | AD43: =+IF('3'!F34>1,"SI","NO") -> NO | AE43: =+IF('3'!F35>1,"SI","NO") -> NO | AF43: =+IF('3'!F36>1,"SI","NO") -> NO | AG43: =+IF('3'!F37>1,"SI","NO") -> NO | AH43: =+IF('3'!F38>1,"SI","NO") -> NO | AI43: =+IF('3'!F39>1,"SI","NO") -> NO | AK43: =+COUNTIF(F43:AJ43,"SI") -> 11 | AL43: =+AK43*E43 -> 275 | AM43: =+AL43*$AM$39 -> 319
A44: 7 | B44: MARTIN EDUARDO VELIZ AREVALO | C44: Supervisor Civil Regional LPZ | D44: 46113 | E44: 25 | F44: =+IF('7'!F10>1,"SI","NO") -> NO | G44: =+IF('7'!F11>1,"SI","NO") -> NO | H44: =+IF('7'!F12>1,"SI","NO") -> NO | I44: =+IF('7'!F13>1,"SI","NO") -> NO | J44: =+IF('7'!F14>1,"SI","NO") -> NO | K44: =+IF('7'!F15>1,"SI","NO") -> NO | L44: =+IF('7'!F16>1,"SI","NO") -> SI | M44: =+IF('7'!F17>1,"SI","NO") -> SI | N44: =+IF('7'!F18>1,"SI","NO") -> SI | O44: =+IF('7'!F19>1,"SI","NO") -> SI | P44: =+IF('7'!F20>1,"SI","NO") -> NO | Q44: =+IF('7'!F21>1,"SI","NO") -> NO | R44: =+IF('7'!F22>1,"SI","NO") -> SI | S44: =+IF('7'!F23>1,"SI","NO") -> SI | T44: =+IF('7'!F24>1,"SI","NO") -> SI | U44: =+IF('7'!F25>1,"SI","NO") -> SI | V44: =+IF('7'!F26>1,"SI","NO") -> SI | W44: =+IF('7'!F27>1,"SI","NO") -> NO | X44: =+IF('7'!F28>1,"SI","NO") -> NO | Y44: =+IF('7'!F29>1,"SI","NO") -> SI | Z44: =+IF('7'!F30>1,"SI","NO") -> NO | AA44: =+IF('7'!F31>1,"SI","NO") -> NO | AB44: =+IF('7'!F32>1,"SI","NO") -> NO | AC44: =+IF('7'!F33>1,"SI","NO") -> NO | AD44: =+IF('7'!F34>1,"SI","NO") -> NO | AE44: =+IF('7'!F35>1,"SI","NO") -> NO | AF44: =+IF('7'!F36>1,"SI","NO") -> NO | AG44: =+IF('7'!F37>1,"SI","NO") -> NO | AH44: =+IF('7'!F38>1,"SI","NO") -> NO | AI44: =+IF('7'!F39>1,"SI","NO") -> NO | AK44: =+COUNTIF(F44:AJ44,"SI") -> 10 | AL44: =+AK44*E44 -> 250 | AM44: =+AL44*$AM$39 -> 290
A45: 10 | B45: DAVID ARIEL PEREDO MIRANDA | C45: Supervisor Elt/Mec Regional | D45: 46113 | E45: 25 | F45: =+IF('10'!F10>1,"SI","NO") -> SI | G45: =+IF('10'!F11>1,"SI","NO") -> SI | H45: =+IF('10'!F12>1,"SI","NO") -> NO | I45: =+IF('10'!F13>1,"SI","NO") -> NO | J45: =+IF('10'!F14>1,"SI","NO") -> NO | K45: =+IF('10'!F15>1,"SI","NO") -> SI | L45: =+IF('10'!F16>1,"SI","NO") -> SI | M45: =+IF('10'!F17>1,"SI","NO") -> SI | N45: =+IF('10'!F18>1,"SI","NO") -> SI | O45: =+IF('10'!F19>1,"SI","NO") -> SI | P45: =+IF('10'!F20>1,"SI","NO") -> NO | Q45: =+IF('10'!F21>1,"SI","NO") -> NO | R45: =+IF('10'!F22>1,"SI","NO") -> SI | S45: =+IF('10'!F23>1,"SI","NO") -> SI | T45: =+IF('10'!F24>1,"SI","NO") -> SI | U45: =+IF('10'!F25>1,"SI","NO") -> SI | V45: =+IF('10'!F26>1,"SI","NO") -> SI | W45: =+IF('10'!F27>1,"SI","NO") -> NO | X45: =+IF('10'!F28>1,"SI","NO") -> NO | Y45: =+IF('10'!F29>1,"SI","NO") -> SI | Z45: =+IF('10'!F30>1,"SI","NO") -> NO | AA45: =+IF('10'!F31>1,"SI","NO") -> NO | AB45: =+IF('10'!F32>1,"SI","NO") -> NO | AC45: =+IF('10'!F33>1,"SI","NO") -> NO | AD45: =+IF('10'!F34>1,"SI","NO") -> NO | AE45: =+IF('10'!F35>1,"SI","NO") -> NO | AF45: =+IF('10'!F36>1,"SI","NO") -> NO | AG45: =+IF('10'!F37>1,"SI","NO") -> NO | AH45: =+IF('10'!F38>1,"SI","NO") -> NO | AI45: =+IF('10'!F39>1,"SI","NO") -> NO | AK45: =+COUNTIF(F45:AJ45,"SI") -> 13 | AL45: =+AK45*E45 -> 325 | AM45: =+AL45*$AM$39 -> 377
AM46: =SUM(AM43:AM45) -> 986
A48: PLANILLA DE ALIMENTACION CBA | AL48: Fee Cont | AM48: 1.16
A50: ITEM | B50: NOMBRE | C50: CARGO | D50: FECHA DE INICIO | E50: P.U. CATERING | F50: DIAS | AK50: TOTAL DIAS | AL50: COSTO TOTAL | AM50: FACTURADO
F51: 1 | G51: 2 | H51: 3 | I51: 4 | J51: 5 | K51: 6 | L51: 7 | M51: 8 | N51: 9 | O51: 10 | P51: 11 | Q51: 12 | R51: 13 | S51: 14 | T51: 15 | U51: 16 | V51: 17 | W51: 18 | X51: 19 | Y51: 20 | Z51: 21 | AA51: 22 | AB51: 23 | AC51: 24 | AD51: 25 | AE51: 26 | AF51: 27 | AG51: 28 | AH51: 29 | AI51: 30
A52: 4 | B52: OSCAR ROLANDO MENDEZ ROCA FARELL | C52: Project Manager Regional CBA | D52: 46113 | E52: 25 | F52: =+IF('4'!F10>1,"SI","NO") -> NO | G52: =+IF('4'!F11>1,"SI","NO") -> NO | H52: =+IF('4'!F12>1,"SI","NO") -> NO | I52: =+IF('4'!F13>1,"SI","NO") -> NO | J52: =+IF('4'!F14>1,"SI","NO") -> NO | K52: =+IF('4'!F15>1,"SI","NO") -> NO | L52: =+IF('4'!F16>1,"SI","NO") -> NO | M52: =+IF('4'!F17>1,"SI","NO") -> NO | N52: =+IF('4'!F18>1,"SI","NO") -> NO | O52: =+IF('4'!F19>1,"SI","NO") -> NO | P52: =+IF('4'!F20>1,"SI","NO") -> NO | Q52: =+IF('4'!F21>1,"SI","NO") -> NO | R52: =+IF('4'!F22>1,"SI","NO") -> NO | S52: =+IF('4'!F23>1,"SI","NO") -> SI | T52: =+IF('4'!F24>1,"SI","NO") -> SI | U52: =+IF('4'!F25>1,"SI","NO") -> SI | V52: =+IF('4'!F26>1,"SI","NO") -> SI | W52: =+IF('4'!F27>1,"SI","NO") -> SI | X52: =+IF('4'!F28>1,"SI","NO") -> NO | Y52: =+IF('4'!F29>1,"SI","NO") -> SI | Z52: =+IF('4'!F30>1,"SI","NO") -> NO | AA52: =+IF('4'!F31>1,"SI","NO") -> NO | AB52: =+IF('4'!F32>1,"SI","NO") -> NO | AC52: =+IF('4'!F33>1,"SI","NO") -> NO | AD52: =+IF('4'!F34>1,"SI","NO") -> NO | AE52: =+IF('4'!F35>1,"SI","NO") -> NO | AF52: =+IF('4'!F36>1,"SI","NO") -> NO | AG52: =+IF('4'!F37>1,"SI","NO") -> NO | AH52: =+IF('4'!F38>1,"SI","NO") -> NO | AI52: =+IF('4'!F39>1,"SI","NO") -> NO | AK52: =+COUNTIF(F52:AJ52,"SI") -> 6 | AL52: =+AK52*E52 -> 150 | AM52: =+AL52*$AM$48 -> 174
A53: 6 | B53: OSCAR FABIAN QUIROGA TAMAYO | C53: Supervisor Civil Regional CBA | D53: 46113 | E53: 25 | F53: =+IF('6'!F10>1,"SI","NO") -> SI | G53: =+IF('6'!F11>1,"SI","NO") -> SI | H53: =+IF('6'!F12>1,"SI","NO") -> NO | I53: =+IF('6'!F13>1,"SI","NO") -> NO | J53: =+IF('6'!F14>1,"SI","NO") -> NO | K53: =+IF('6'!F15>1,"SI","NO") -> SI | L53: =+IF('6'!F16>1,"SI","NO") -> SI | M53: =+IF('6'!F17>1,"SI","NO") -> SI | N53: =+IF('6'!F18>1,"SI","NO") -> SI | O53: =+IF('6'!F19>1,"SI","NO") -> SI | P53: =+IF('6'!F20>1,"SI","NO") -> NO | Q53: =+IF('6'!F21>1,"SI","NO") -> NO | R53: =+IF('6'!F22>1,"SI","NO") -> SI | S53: =+IF('6'!F23>1,"SI","NO") -> SI | T53: =+IF('6'!F24>1,"SI","NO") -> SI | U53: =+IF('6'!F25>1,"SI","NO") -> SI | V53: =+IF('6'!F26>1,"SI","NO") -> SI | W53: =+IF('6'!F27>1,"SI","NO") -> SI | X53: =+IF('6'!F28>1,"SI","NO") -> NO | Y53: =+IF('6'!F29>1,"SI","NO") -> SI | Z53: =+IF('6'!F30>1,"SI","NO") -> NO | AA53: =+IF('6'!F31>1,"SI","NO") -> NO | AB53: =+IF('6'!F32>1,"SI","NO") -> NO | AC53: =+IF('6'!F33>1,"SI","NO") -> NO | AD53: =+IF('6'!F34>1,"SI","NO") -> NO | AE53: =+IF('6'!F35>1,"SI","NO") -> NO | AF53: =+IF('6'!F36>1,"SI","NO") -> NO | AG53: =+IF('6'!F37>1,"SI","NO") -> NO | AH53: =+IF('6'!F38>1,"SI","NO") -> NO | AI53: =+IF('6'!F39>1,"SI","NO") -> NO | AK53: =+COUNTIF(F53:AJ53,"SI") -> 14 | AL53: =+AK53*E53 -> 350 | AM53: =+AL53*$AM$48 -> 406
A54: 11 | B54: ERIN CALLEJAS VELASQUEZ | C54: Supervisor Elt/Mec Regional | D54: 46113 | E54: 25 | F54: =+IF('11'!F10>1,"SI","NO") -> SI | G54: =+IF('11'!F11>1,"SI","NO") -> NO | H54: =+IF('11'!F12>1,"SI","NO") -> NO | I54: =+IF('11'!F13>1,"SI","NO") -> NO | J54: =+IF('11'!F14>1,"SI","NO") -> NO | K54: =+IF('11'!F15>1,"SI","NO") -> SI | L54: =+IF('11'!F16>1,"SI","NO") -> SI | M54: =+IF('11'!F17>1,"SI","NO") -> SI | N54: =+IF('11'!F18>1,"SI","NO") -> SI | O54: =+IF('11'!F19>1,"SI","NO") -> SI | P54: =+IF('11'!F20>1,"SI","NO") -> NO | Q54: =+IF('11'!F21>1,"SI","NO") -> NO | R54: =+IF('11'!F22>1,"SI","NO") -> SI | S54: =+IF('11'!F23>1,"SI","NO") -> SI | T54: =+IF('11'!F24>1,"SI","NO") -> SI | U54: =+IF('11'!F25>1,"SI","NO") -> SI | V54: =+IF('11'!F26>1,"SI","NO") -> SI | W54: =+IF('11'!F27>1,"SI","NO") -> NO | X54: =+IF('11'!F28>1,"SI","NO") -> NO | Y54: =+IF('11'!F29>1,"SI","NO") -> SI | Z54: =+IF('11'!F30>1,"SI","NO") -> NO | AA54: =+IF('11'!F31>1,"SI","NO") -> NO | AB54: =+IF('11'!F32>1,"SI","NO") -> NO | AC54: =+IF('11'!F33>1,"SI","NO") -> NO | AD54: =+IF('11'!F34>1,"SI","NO") -> NO | AE54: =+IF('11'!F35>1,"SI","NO") -> NO | AF54: =+IF('11'!F36>1,"SI","NO") -> NO | AG54: =+IF('11'!F37>1,"SI","NO") -> NO | AH54: =+IF('11'!F38>1,"SI","NO") -> NO | AI54: =+IF('11'!F39>1,"SI","NO") -> NO | AK54: =+COUNTIF(F54:AJ54,"SI") -> 12 | AL54: =+AK54*E54 -> 300 | AM54: =+AL54*$AM$48 -> 348
AM55: =SUM(AM52:AM54) -> 928
A57: PLANILLA DE ALIMENTACION SCZ | AL57: Fee Cont | AM57: 1.16
A59: ITEM | B59: NOMBRE | C59: CARGO | D59: FECHA DE INICIO | E59: P.U. CATERING | F59: DIAS | AK59: TOTAL DIAS | AL59: COSTO TOTAL | AM59: FACTURADO
F60: 1 | G60: 2 | H60: 3 | I60: 4 | J60: 5 | K60: 6 | L60: 7 | M60: 8 | N60: 9 | O60: 10 | P60: 11 | Q60: 12 | R60: 13 | S60: 14 | T60: 15 | U60: 16 | V60: 17 | W60: 18 | X60: 19 | Y60: 20 | Z60: 21 | AA60: 22 | AB60: 23 | AC60: 24 | AD60: 25 | AE60: 26 | AF60: 27 | AG60: 28 | AH60: 29 | AI60: 30
A61: 1 | B61: RAMIRO ARMANDO SUAREZ RIBERO | C61: Project Manager Central | D61: 46113 | E61: 25 | F61: =+IF('1'!F10>1,"SI","NO") -> SI | G61: =+IF('1'!F11>1,"SI","NO") -> SI | H61: =+IF('1'!F12>1,"SI","NO") -> NO | I61: =+IF('1'!F13>1,"SI","NO") -> NO | J61: =+IF('1'!F14>1,"SI","NO") -> NO | K61: =+IF('1'!F15>1,"SI","NO") -> SI | L61: =+IF('1'!F16>1,"SI","NO") -> SI | M61: =+IF('1'!F17>1,"SI","NO") -> SI | N61: =+IF('1'!F18>1,"SI","NO") -> SI | O61: =+IF('1'!F19>1,"SI","NO") -> SI | P61: =+IF('1'!F20>1,"SI","NO") -> NO | Q61: =+IF('1'!F21>1,"SI","NO") -> NO | R61: =+IF('1'!F22>1,"SI","NO") -> SI | S61: =+IF('1'!F23>1,"SI","NO") -> SI | T61: =+IF('1'!F24>1,"SI","NO") -> SI | U61: =+IF('1'!F25>1,"SI","NO") -> SI | V61: =+IF('1'!F26>1,"SI","NO") -> SI | W61: =+IF('1'!F27>1,"SI","NO") -> SI | X61: =+IF('1'!F28>1,"SI","NO") -> NO | Y61: =+IF('1'!F29>1,"SI","NO") -> SI | Z61: =+IF('1'!F30>1,"SI","NO") -> NO | AA61: =+IF('1'!F31>1,"SI","NO") -> NO | AB61: =+IF('1'!F32>1,"SI","NO") -> NO | AC61: =+IF('1'!F33>1,"SI","NO") -> NO | AD61: =+IF('1'!F34>1,"SI","NO") -> NO | AE61: =+IF('1'!F35>1,"SI","NO") -> NO | AF61: =+IF('1'!F36>1,"SI","NO") -> NO | AG61: =+IF('1'!F37>1,"SI","NO") -> NO | AH61: =+IF('1'!F38>1,"SI","NO") -> NO | AI61: =+IF('1'!F39>1,"SI","NO") -> NO | AK61: =+COUNTIF(F61:AJ61,"SI") -> 14 | AL61: =+AK61*E61 -> 350 | AM61: =+AL61*$AM$57 -> 406
A62: 2 | B62: ERICKA YOSELIN FLORES VACA | C62: Project Manager Regional SCZ | D62: 46113 | E62: 25 | F62: =+IF('2'!F10>1,"SI","NO") -> NO | G62: =+IF('2'!F11>1,"SI","NO") -> NO | H62: =+IF('2'!F12>1,"SI","NO") -> NO | I62: =+IF('2'!F13>1,"SI","NO") -> NO | J62: =+IF('2'!F14>1,"SI","NO") -> NO | K62: =+IF('2'!F15>1,"SI","NO") -> SI | L62: =+IF('2'!F16>1,"SI","NO") -> SI | M62: =+IF('2'!F17>1,"SI","NO") -> SI | N62: =+IF('2'!F18>1,"SI","NO") -> SI | O62: =+IF('2'!F19>1,"SI","NO") -> SI | P62: =+IF('2'!F20>1,"SI","NO") -> NO | Q62: =+IF('2'!F21>1,"SI","NO") -> NO | R62: =+IF('2'!F22>1,"SI","NO") -> SI | S62: =+IF('2'!F23>1,"SI","NO") -> SI | T62: =+IF('2'!F24>1,"SI","NO") -> SI | U62: =+IF('2'!F25>1,"SI","NO") -> SI | V62: =+IF('2'!F26>1,"SI","NO") -> SI | W62: =+IF('2'!F27>1,"SI","NO") -> NO | X62: =+IF('2'!F28>1,"SI","NO") -> NO | Y62: =+IF('2'!F29>1,"SI","NO") -> SI | Z62: =+IF('2'!F30>1,"SI","NO") -> NO | AA62: =+IF('2'!F31>1,"SI","NO") -> NO | AB62: =+IF('2'!F32>1,"SI","NO") -> NO | AC62: =+IF('2'!F33>1,"SI","NO") -> NO | AD62: =+IF('2'!F34>1,"SI","NO") -> NO | AE62: =+IF('2'!F35>1,"SI","NO") -> NO | AF62: =+IF('2'!F36>1,"SI","NO") -> NO | AG62: =+IF('2'!F37>1,"SI","NO") -> NO | AH62: =+IF('2'!F38>1,"SI","NO") -> NO | AI62: =+IF('2'!F39>1,"SI","NO") -> NO | AK62: =+COUNTIF(F62:AJ62,"SI") -> 11 | AL62: =+AK62*E62 -> 275 | AM62: =+AL62*$AM$57 -> 319
A63: 5 | B63: JORGE LUIS ROJAS DÁVILA | C63: Supervisor Civil Regional SCZ | D63: 46113 | E63: 25 | F63: =+IF('5'!F10>1,"SI","NO") -> SI | G63: =+IF('5'!F11>1,"SI","NO") -> NO | H63: =+IF('5'!F12>1,"SI","NO") -> NO | I63: =+IF('5'!F13>1,"SI","NO") -> NO | J63: =+IF('5'!F14>1,"SI","NO") -> NO | K63: =+IF('5'!F15>1,"SI","NO") -> SI | L63: =+IF('5'!F16>1,"SI","NO") -> SI | M63: =+IF('5'!F17>1,"SI","NO") -> SI | N63: =+IF('5'!F18>1,"SI","NO") -> SI | O63: =+IF('5'!F19>1,"SI","NO") -> SI | P63: =+IF('5'!F20>1,"SI","NO") -> NO | Q63: =+IF('5'!F21>1,"SI","NO") -> NO | R63: =+IF('5'!F22>1,"SI","NO") -> SI | S63: =+IF('5'!F23>1,"SI","NO") -> SI | T63: =+IF('5'!F24>1,"SI","NO") -> SI | U63: =+IF('5'!F25>1,"SI","NO") -> SI | V63: =+IF('5'!F26>1,"SI","NO") -> SI | W63: =+IF('5'!F27>1,"SI","NO") -> NO | X63: =+IF('5'!F28>1,"SI","NO") -> NO | Y63: =+IF('5'!F29>1,"SI","NO") -> SI | Z63: =+IF('5'!F30>1,"SI","NO") -> NO | AA63: =+IF('5'!F31>1,"SI","NO") -> NO | AB63: =+IF('5'!F32>1,"SI","NO") -> NO | AC63: =+IF('5'!F33>1,"SI","NO") -> NO | AD63: =+IF('5'!F34>1,"SI","NO") -> NO | AE63: =+IF('5'!F35>1,"SI","NO") -> NO | AF63: =+IF('5'!F36>1,"SI","NO") -> NO | AG63: =+IF('5'!F37>1,"SI","NO") -> NO | AH63: =+IF('5'!F38>1,"SI","NO") -> NO | AI63: =+IF('5'!F39>1,"SI","NO") -> NO | AK63: =+COUNTIF(F63:AJ63,"SI") -> 12 | AL63: =+AK63*E63 -> 300 | AM63: =+AL63*$AM$57 -> 348
A64: 8 | B64: RAÚL RAIMUNDO PARRAGA ANTEZANA | C64: Supervisor Eléctrico Regional | D64: 46113 | E64: 25 | F64: =+IF('8'!F10>1,"SI","NO") -> SI | G64: =+IF('8'!F11>1,"SI","NO") -> SI | H64: =+IF('8'!F12>1,"SI","NO") -> NO | I64: =+IF('8'!F13>1,"SI","NO") -> NO | J64: =+IF('8'!F14>1,"SI","NO") -> NO | K64: =+IF('8'!F15>1,"SI","NO") -> SI | L64: =+IF('8'!F16>1,"SI","NO") -> SI | M64: =+IF('8'!F17>1,"SI","NO") -> SI | N64: =+IF('8'!F18>1,"SI","NO") -> SI | O64: =+IF('8'!F19>1,"SI","NO") -> SI | P64: =+IF('8'!F20>1,"SI","NO") -> NO | Q64: =+IF('8'!F21>1,"SI","NO") -> NO | R64: =+IF('8'!F22>1,"SI","NO") -> SI | S64: =+IF('8'!F23>1,"SI","NO") -> NO | T64: =+IF('8'!F24>1,"SI","NO") -> SI | U64: =+IF('8'!F25>1,"SI","NO") -> SI | V64: =+IF('8'!F26>1,"SI","NO") -> SI | W64: =+IF('8'!F27>1,"SI","NO") -> NO | X64: =+IF('8'!F28>1,"SI","NO") -> NO | Y64: =+IF('8'!F29>1,"SI","NO") -> SI | Z64: =+IF('8'!F30>1,"SI","NO") -> NO | AA64: =+IF('8'!F31>1,"SI","NO") -> NO | AB64: =+IF('8'!F32>1,"SI","NO") -> NO | AC64: =+IF('8'!F33>1,"SI","NO") -> NO | AD64: =+IF('8'!F34>1,"SI","NO") -> NO | AE64: =+IF('8'!F35>1,"SI","NO") -> NO | AF64: =+IF('8'!F36>1,"SI","NO") -> NO | AG64: =+IF('8'!F37>1,"SI","NO") -> NO | AH64: =+IF('8'!F38>1,"SI","NO") -> NO | AI64: =+IF('8'!F39>1,"SI","NO") -> NO | AK64: =+COUNTIF(F64:AJ64,"SI") -> 12 | AL64: =+AK64*E64 -> 300 | AM64: =+AL64*$AM$57 -> 348
A65: 9 | B65: ABRAHAM QUENA CABRERA | C65: Supervisor Mecánico Regional | D65: 46113 | E65: 25 | F65: =+IF('9'!F10>1,"SI","NO") -> SI | G65: =+IF('9'!F11>1,"SI","NO") -> SI | H65: =+IF('9'!F12>1,"SI","NO") -> NO | I65: =+IF('9'!F13>1,"SI","NO") -> NO | J65: =+IF('9'!F14>1,"SI","NO") -> NO | K65: =+IF('9'!F15>1,"SI","NO") -> SI | L65: =+IF('9'!F16>1,"SI","NO") -> SI | M65: =+IF('9'!F17>1,"SI","NO") -> SI | N65: =+IF('9'!F18>1,"SI","NO") -> SI | O65: =+IF('9'!F19>1,"SI","NO") -> SI | P65: =+IF('9'!F20>1,"SI","NO") -> NO | Q65: =+IF('9'!F21>1,"SI","NO") -> NO | R65: =+IF('9'!F22>1,"SI","NO") -> SI | S65: =+IF('9'!F23>1,"SI","NO") -> SI | T65: =+IF('9'!F24>1,"SI","NO") -> SI | U65: =+IF('9'!F25>1,"SI","NO") -> SI | V65: =+IF('9'!F26>1,"SI","NO") -> SI | W65: =+IF('9'!F27>1,"SI","NO") -> NO | X65: =+IF('9'!F28>1,"SI","NO") -> NO | Y65: =+IF('9'!F29>1,"SI","NO") -> SI | Z65: =+IF('9'!F30>1,"SI","NO") -> NO | AA65: =+IF('9'!F31>1,"SI","NO") -> NO | AB65: =+IF('9'!F32>1,"SI","NO") -> NO | AC65: =+IF('9'!F33>1,"SI","NO") -> NO | AD65: =+IF('9'!F34>1,"SI","NO") -> NO | AE65: =+IF('9'!F35>1,"SI","NO") -> NO | AF65: =+IF('9'!F36>1,"SI","NO") -> NO | AG65: =+IF('9'!F37>1,"SI","NO") -> NO | AH65: =+IF('9'!F38>1,"SI","NO") -> NO | AI65: =+IF('9'!F39>1,"SI","NO") -> NO | AK65: =+COUNTIF(F65:AJ65,"SI") -> 13 | AL65: =+AK65*E65 -> 325 | AM65: =+AL65*$AM$57 -> 377
A66: 12 | B66: JOSUÉ CONRRADO FERNÁNDEZ SOTEZ | C66: Encargado de Almacén | D66: 46113 | E66: 25 | F66: =+IF('12'!F10>1,"SI","NO") -> SI | G66: =+IF('12'!F11>1,"SI","NO") -> SI | H66: =+IF('12'!F12>1,"SI","NO") -> NO | I66: =+IF('12'!F13>1,"SI","NO") -> NO | J66: =+IF('12'!F14>1,"SI","NO") -> NO | K66: =+IF('12'!F15>1,"SI","NO") -> SI | L66: =+IF('12'!F16>1,"SI","NO") -> SI | M66: =+IF('12'!F17>1,"SI","NO") -> SI | N66: =+IF('12'!F18>1,"SI","NO") -> SI | O66: =+IF('12'!F19>1,"SI","NO") -> SI | P66: =+IF('12'!F20>1,"SI","NO") -> SI | Q66: =+IF('12'!F21>1,"SI","NO") -> NO | R66: =+IF('12'!F22>1,"SI","NO") -> SI | S66: =+IF('12'!F23>1,"SI","NO") -> SI | T66: =+IF('12'!F24>1,"SI","NO") -> SI | U66: =+IF('12'!F25>1,"SI","NO") -> SI | V66: =+IF('12'!F26>1,"SI","NO") -> SI | W66: =+IF('12'!F27>1,"SI","NO") -> SI | X66: =+IF('12'!F28>1,"SI","NO") -> NO | Y66: =+IF('12'!F29>1,"SI","NO") -> SI | Z66: =+IF('12'!F30>1,"SI","NO") -> NO | AA66: =+IF('12'!F31>1,"SI","NO") -> NO | AB66: =+IF('12'!F32>1,"SI","NO") -> NO | AC66: =+IF('12'!F33>1,"SI","NO") -> NO | AD66: =+IF('12'!F34>1,"SI","NO") -> NO | AE66: =+IF('12'!F35>1,"SI","NO") -> NO | AF66: =+IF('12'!F36>1,"SI","NO") -> NO | AG66: =+IF('12'!F37>1,"SI","NO") -> NO | AH66: =+IF('12'!F38>1,"SI","NO") -> NO | AI66: =+IF('12'!F39>1,"SI","NO") -> NO | AK66: =+COUNTIF(F66:AJ66,"SI") -> 15 | AL66: =+AK66*E66 -> 375 | AM66: =+AL66*$AM$57 -> 435
AM67: =SUM(AM61:AM66) -> 2233
W69: TOTAL FACTURACION | AL69: =+AM26+P37+AM36+AM46+AM55+AM67 -> 142627.48
W71: ="Son : " & TEXT(AL69,"#,##0.00") & " Bolivianos" -> Son : 142,627.48 Bolivianos
C77: REDLINE GENERAL SERVICES | O77: FIRMA APROBACION EMBOL | AC77: FIRMA APROBACION EMBOL

Sheet 1
A2: PLANILLA CONTROL DE ASISTENCIA
A4: ITEM | B4: 1
A5: NOMBRE | B5: RAMIRO ARMANDO SUAREZ RIBERO
A6: CARGO | B6: Project Manager Central
A7: HABER BASICO | B7: 9500 | C7: Bs.
A9: FECHA | B9: DIA | C9: HORA INGRESO | D9: HORA SALIDA | E9: REFRIGERIO | F9: HORAS TRABAJO | G9: ATRASOS MINUTOS | H9: OBSERVACIONES
A10: 46113 | B10: =+A10 -> 46113 | C10: 0.33333333 | D10: 0.70833333 | E10: 1 | F10: =+(D10-C10)*24-E10 -> 8 | G10: =+IF(C10>0.333333333333333,+(C10-0.333333333333333)*24*60,"0") -> 0
A11: 46114 | B11: =+A11 -> 46114 | C11: 0.33333333 | D11: 0.70833333 | E11: 1 | F11: =+(D11-C11)*24-E11 -> 8 | G11: =+IF(C11>0.333333333333333,+(C11-0.333333333333333)*24*60,"0") -> 0
A12: 46115 | B12: =+A12 -> 46115 | F12: =+(D12-C12)*24-E12 -> 0 | G12: =+IF(C12>0.333333333333333,+(C12-0.333333333333333)*24*60,"0") -> 0 | H12: Feriado: Semana Santa
A13: 46116 | B13: =+A13 -> 46116 | F13: =+(D13-C13)*24-E13 -> 0 | G13: =+IF(C13>0.333333333333333,+(C13-0.333333333333333)*24*60,"0") -> 0
A14: 46117 | B14: =+A14 -> 46117 | F14: =+(D14-C14)*24-E14 -> 0 | G14: =+IF(C14>0.333333333333333,+(C14-0.333333333333333)*24*60,"0") -> 0
A15: 46118 | B15: =+A15 -> 46118 | C15: 0.35972222 | D15: 0.77083333 | E15: 1 | F15: =+(D15-C15)*24-E15 -> 8.8666667 | G15: =+IF(C15>0.333333333333333,+(C15-0.333333333333333)*24*60,"0") -> 38
A16: 46119 | B16: =+A16 -> 46119 | C16: 0.32638889 | D16: 0.7625 | E16: 1 | F16: =+(D16-C16)*24-E16 -> 9.4666667 | G16: =+IF(C16>0.333333333333333,+(C16-0.333333333333333)*24*60,"0") -> 0
A17: 46120 | B17: =+A17 -> 46120 | C17: 0.33680556 | D17: 0.78958333 | E17: 1 | F17: =+(D17-C17)*24-E17 -> 9.8666667 | G17: =+IF(C17>0.333333333333333,+(C17-0.333333333333333)*24*60,"0") -> 5
A18: 46121 | B18: =+A18 -> 46121 | C18: 0.32361111 | D18: 0.76805556 | E18: 1 | F18: =+(D18-C18)*24-E18 -> 9.6666667 | G18: =+IF(C18>0.333333333333333,+(C18-0.333333333333333)*24*60,"0") -> 0
A19: 46122 | B19: =+A19 -> 46122 | C19: 0.32152778 | D19: 0.76527778 | E19: 1 | F19: =+(D19-C19)*24-E19 -> 9.65 | G19: =+IF(C19>0.333333333333333,+(C19-0.333333333333333)*24*60,"0") -> 0
A20: 46123 | B20: =+A20 -> 46123 | F20: =+(D20-C20)*24-E20 -> 0 | G20: =+IF(C20>0.333333333333333,+(C20-0.333333333333333)*24*60,"0") -> 0
A21: 46124 | B21: =+A21 -> 46124 | F21: =+(D21-C21)*24-E21 -> 0 | G21: =+IF(C21>0.333333333333333,+(C21-0.333333333333333)*24*60,"0") -> 0
A22: 46125 | B22: =+A22 -> 46125 | C22: 0.32569444 | D22: 0.75277778 | E22: 1 | F22: =+(D22-C22)*24-E22 -> 9.25 | G22: =+IF(C22>0.333333333333333,+(C22-0.333333333333333)*24*60,"0") -> 0
A23: 46126 | B23: =+A23 -> 46126 | C23: 0.33472222 | D23: 0.775 | E23: 1 | F23: =+(D23-C23)*24-E23 -> 9.5666667 | G23: =+IF(C23>0.333333333333333,+(C23-0.333333333333333)*24*60,"0") -> 2
A24: 46127 | B24: =+A24 -> 46127 | C24: 0.32291667 | D24: 0.75416667 | E24: 1 | F24: =+(D24-C24)*24-E24 -> 9.35 | G24: =+IF(C24>0.333333333333333,+(C24-0.333333333333333)*24*60,"0") -> 0
A25: 46128 | B25: =+A25 -> 46128 | C25: 0.32986111 | D25: 0.75833333 | E25: 1 | F25: =+(D25-C25)*24-E25 -> 9.2833333 | G25: =+IF(C25>0.333333333333333,+(C25-0.333333333333333)*24*60,"0") -> 0
A26: 46129 | B26: =+A26 -> 46129 | C26: 0.32916667 | D26: 0.75763889 | E26: 1 | F26: =+(D26-C26)*24-E26 -> 9.2833333 | G26: =+IF(C26>0.333333333333333,+(C26-0.333333333333333)*24*60,"0") -> 0
A27: 46130 | B27: =+A27 -> 46130 | C27: 0.3625 | D27: 0.45902778 | E27: 1 | F27: =+(D27-C27)*24-E27 -> 1.3166667 | G27: =+IF(C27>0.333333333333333,+(C27-0.333333333333333)*24*60,"0") -> 42
A28: 46131 | B28: =+A28 -> 46131 | F28: =+(D28-C28)*24-E28 -> 0 | G28: =+IF(C28>0.333333333333333,+(C28-0.333333333333333)*24*60,"0") -> 0
A29: 46132 | B29: =+A29 -> 46132 | C29: 0.34652778 | D29: 0.78194444 | E29: 1 | F29: =+(D29-C29)*24-E29 -> 9.45 | G29: =+IF(C29>0.333333333333333,+(C29-0.333333333333333)*24*60,"0") -> 19
A30: 46133 | B30: =+A30 -> 46133 | F30: =+(D30-C30)*24-E30 -> 0 | G30: =+IF(C30>0.333333333333333,+(C30-0.333333333333333)*24*60,"0") -> 0
A31: 46134 | B31: =+A31 -> 46134 | F31: =+(D31-C31)*24-E31 -> 0 | G31: =+IF(C31>0.333333333333333,+(C31-0.333333333333333)*24*60,"0") -> 0
A32: 46135 | B32: =+A32 -> 46135 | F32: =+(D32-C32)*24-E32 -> 0 | G32: =+IF(C32>0.333333333333333,+(C32-0.333333333333333)*24*60,"0") -> 0
A33: 46136 | B33: =+A33 -> 46136 | F33: =+(D33-C33)*24-E33 -> 0 | G33: =+IF(C33>0.333333333333333,+(C33-0.333333333333333)*24*60,"0") -> 0
A34: 46137 | B34: =+A34 -> 46137 | F34: =+(D34-C34)*24-E34 -> 0 | G34: =+IF(C34>0.333333333333333,+(C34-0.333333333333333)*24*60,"0") -> 0
A35: 46138 | B35: =+A35 -> 46138 | F35: =+(D35-C35)*24-E35 -> 0 | G35: =+IF(C35>0.333333333333333,+(C35-0.333333333333333)*24*60,"0") -> 0
A36: 46139 | B36: =+A36 -> 46139 | F36: =+(D36-C36)*24-E36 -> 0 | G36: =+IF(C36>0.333333333333333,+(C36-0.333333333333333)*24*60,"0") -> 0
A37: 46140 | B37: =+A37 -> 46140 | F37: =+(D37-C37)*24-E37 -> 0 | G37: =+IF(C37>0.333333333333333,+(C37-0.333333333333333)*24*60,"0") -> 0
A38: 46141 | B38: =+A38 -> 46141 | F38: =+(D38-C38)*24-E38 -> 0 | G38: =+IF(C38>0.333333333333333,+(C38-0.333333333333333)*24*60,"0") -> 0
A39: 46142 | B39: =+A39 -> 46142 | F39: =+(D39-C39)*24-E39 -> 0 | G39: =+IF(C39>0.333333333333333,+(C39-0.333333333333333)*24*60,"0") -> 0
A40: TOTAL DIAS TRABAJADOS | C40: =+COUNT(C10:C39) -> 14
A41: TOTAL HORAS TRABAJADAS | C41: =SUM(F10:F39) -> 121.01667
A42: ATRASOS | C42: =SUM(G10:G39) -> 106

Sheet 2
A2: PLANILLA CONTROL DE ASISTENCIA
A4: ITEM | B4: 2
A5: NOMBRE | B5: ERICKA YOSELIN FLORES VACA
A6: CARGO | B6: Project Manager Regional SCZ
A7: HABER BASICO | B7: 8000 | C7: Bs.
A9: FECHA | B9: DIA | C9: HORA INGRESO | D9: HORA SALIDA | E9: REFRIGERIO | F9: HORAS TRABAJO | G9: ATRASOS MINUTOS | H9: OBSERVACIONES
A10: 46113 | B10: =+A10 -> 46113 | F10: =+(D10-C10)*24-E10 -> 0 | G10: =+IF(C10>0.333333333333333,+(C10-0.333333333333333)*24*60,"0") -> 0
A11: 46114 | B11: =+A11 -> 46114 | F11: =+(D11-C11)*24-E11 -> 0 | G11: =+IF(C11>0.333333333333333,+(C11-0.333333333333333)*24*60,"0") -> 0
A12: 46115 | B12: =+A12 -> 46115 | F12: =+(D12-C12)*24-E12 -> 0 | G12: =+IF(C12>0.333333333333333,+(C12-0.333333333333333)*24*60,"0") -> 0 | H12: Feriado: Semana Santa
A13: 46116 | B13: =+A13 -> 46116 | F13: =+(D13-C13)*24-E13 -> 0 | G13: =+IF(C13>0.333333333333333,+(C13-0.333333333333333)*24*60,"0") -> 0
A14: 46117 | B14: =+A14 -> 46117 | F14: =+(D14-C14)*24-E14 -> 0 | G14: =+IF(C14>0.333333333333333,+(C14-0.333333333333333)*24*60,"0") -> 0
A15: 46118 | B15: =+A15 -> 46118 | C15: 0.41666667 | D15: 0.77847222 | E15: 1 | F15: =+(D15-C15)*24-E15 -> 7.6833333 | G15: =+IF(C15>0.333333333333333,+(C15-0.333333333333333)*24*60,"0") -> 120
A16: 46119 | B16: =+A16 -> 46119 | C16: 0.33263889 | D16: 0.77847222 | E16: 1 | F16: =+(D16-C16)*24-E16 -> 9.7 | G16: =+IF(C16>0.333333333333333,+(C16-0.333333333333333)*24*60,"0") -> 0
A17: 46120 | B17: =+A17 -> 46120 | C17: 0.33263889 | D17: 0.78819444 | E17: 1 | F17: =+(D17-C17)*24-E17 -> 9.9333333 | G17: =+IF(C17>0.333333333333333,+(C17-0.333333333333333)*24*60,"0") -> 0
A18: 46121 | B18: =+A18 -> 46121 | C18: 0.33402778 | D18: 0.77847222 | E18: 1 | F18: =+(D18-C18)*24-E18 -> 9.6666667 | G18: =+IF(C18>0.333333333333333,+(C18-0.333333333333333)*24*60,"0") -> 1
A19: 46122 | B19: =+A19 -> 46122 | C19: 0.33472222 | D19: 0.78055556 | E19: 1 | F19: =+(D19-C19)*24-E19 -> 9.7 | G19: =+IF(C19>0.333333333333333,+(C19-0.333333333333333)*24*60,"0") -> 2
A20: 46123 | B20: =+A20 -> 46123 | F20: =+(D20-C20)*24-E20 -> 0 | G20: =+IF(C20>0.333333333333333,+(C20-0.333333333333333)*24*60,"0") -> 0
A21: 46124 | B21: =+A21 -> 46124 | F21: =+(D21-C21)*24-E21 -> 0 | G21: =+IF(C21>0.333333333333333,+(C21-0.333333333333333)*24*60,"0") -> 0
A22: 46125 | B22: =+A22 -> 46125 | C22: 0.33611111 | D22: 0.78055556 | E22: 1 | F22: =+(D22-C22)*24-E22 -> 9.6666667 | G22: =+IF(C22>0.333333333333333,+(C22-0.333333333333333)*24*60,"0") -> 4
A23: 46126 | B23: =+A23 -> 46126 | C23: 0.33472222 | D23: 0.77847222 | E23: 1 | F23: =+(D23-C23)*24-E23 -> 9.65 | G23: =+IF(C23>0.333333333333333,+(C23-0.333333333333333)*24*60,"0") -> 2
A24: 46127 | B24: =+A24 -> 46127 | C24: 0.33611111 | D24: 0.78888889 | E24: 1 | F24: =+(D24-C24)*24-E24 -> 9.8666667 | G24: =+IF(C24>0.333333333333333,+(C24-0.333333333333333)*24*60,"0") -> 4
A25: 46128 | B25: =+A25 -> 46128 | C25: 0.33402778 | D25: 0.79791667 | E25: 1 | F25: =+(D25-C25)*24-E25 -> 10.133333 | G25: =+IF(C25>0.333333333333333,+(C25-0.333333333333333)*24*60,"0") -> 1
A26: 46129 | B26: =+A26 -> 46129 | C26: 0.34166667 | D26: 0.80069444 | E26: 1 | F26: =+(D26-C26)*24-E26 -> 10.016667 | G26: =+IF(C26>0.333333333333333,+(C26-0.333333333333333)*24*60,"0") -> 12
A27: 46130 | B27: =+A27 -> 46130 | C27: 0.37916667 | D27: 0.45694444 | E27: 1 | F27: =+(D27-C27)*24-E27 -> 0.86666667 | G27: =+IF(C27>0.333333333333333,+(C27-0.333333333333333)*24*60,"0") -> 66
A28: 46131 | B28: =+A28 -> 46131 | F28: =+(D28-C28)*24-E28 -> 0 | G28: =+IF(C28>0.333333333333333,+(C28-0.333333333333333)*24*60,"0") -> 0
A29: 46132 | B29: =+A29 -> 46132 | C29: 0.34375 | D29: 0.78680556 | E29: 1 | F29: =+(D29-C29)*24-E29 -> 9.6333333 | G29: =+IF(C29>0.333333333333333,+(C29-0.333333333333333)*24*60,"0") -> 15
A30: 46133 | B30: =+A30 -> 46133 | F30: =+(D30-C30)*24-E30 -> 0 | G30: =+IF(C30>0.333333333333333,+(C30-0.333333333333333)*24*60,"0") -> 0
A31: 46134 | B31: =+A31 -> 46134 | F31: =+(D31-C31)*24-E31 -> 0 | G31: =+IF(C31>0.333333333333333,+(C31-0.333333333333333)*24*60,"0") -> 0
A32: 46135 | B32: =+A32 -> 46135 | F32: =+(D32-C32)*24-E32 -> 0 | G32: =+IF(C32>0.333333333333333,+(C32-0.333333333333333)*24*60,"0") -> 0
A33: 46136 | B33: =+A33 -> 46136 | F33: =+(D33-C33)*24-E33 -> 0 | G33: =+IF(C33>0.333333333333333,+(C33-0.333333333333333)*24*60,"0") -> 0
A34: 46137 | B34: =+A34 -> 46137 | F34: =+(D34-C34)*24-E34 -> 0 | G34: =+IF(C34>0.333333333333333,+(C34-0.333333333333333)*24*60,"0") -> 0
A35: 46138 | B35: =+A35 -> 46138 | F35: =+(D35-C35)*24-E35 -> 0 | G35: =+IF(C35>0.333333333333333,+(C35-0.333333333333333)*24*60,"0") -> 0
A36: 46139 | B36: =+A36 -> 46139 | F36: =+(D36-C36)*24-E36 -> 0 | G36: =+IF(C36>0.333333333333333,+(C36-0.333333333333333)*24*60,"0") -> 0
A37: 46140 | B37: =+A37 -> 46140 | F37: =+(D37-C37)*24-E37 -> 0 | G37: =+IF(C37>0.333333333333333,+(C37-0.333333333333333)*24*60,"0") -> 0
A38: 46141 | B38: =+A38 -> 46141 | F38: =+(D38-C38)*24-E38 -> 0 | G38: =+IF(C38>0.333333333333333,+(C38-0.333333333333333)*24*60,"0") -> 0
A39: 46142 | B39: =+A39 -> 46142 | F39: =+(D39-C39)*24-E39 -> 0 | G39: =+IF(C39>0.333333333333333,+(C39-0.333333333333333)*24*60,"0") -> 0
A40: TOTAL DIAS TRABAJADOS | C40: =+COUNT(C10:C39) -> 12
A41: TOTAL HORAS TRABAJADAS | C41: =SUM(F10:F39) -> 106.51667
A42: ATRASOS | C42: =SUM(G10:G39) -> 227

Sheet 3
A2: PLANILLA CONTROL DE ASISTENCIA
A4: ITEM | B4: 3
A5: NOMBRE | B5: CESAR JOSÉ MOYA VARGAS
A6: CARGO | B6: Project Manager Regional LPZ
A7: HABER BASICO | B7: 8000 | C7: Bs.
A9: FECHA | B9: DIA | C9: HORA INGRESO | D9: HORA SALIDA | E9: REFRIGERIO | F9: HORAS TRABAJO | G9: ATRASOS MINUTOS | H9: OBSERVACIONES
A10: 46113 | B10: =+A10 -> 46113 | F10: =+(D10-C10)*24-E10 -> 0 | G10: =+IF(C10>0.333333333333333,+(C10-0.333333333333333)*24*60,"0") -> 0
A11: 46114 | B11: =+A11 -> 46114 | F11: =+(D11-C11)*24-E11 -> 0 | G11: =+IF(C11>0.333333333333333,+(C11-0.333333333333333)*24*60,"0") -> 0
A12: 46115 | B12: =+A12 -> 46115 | F12: =+(D12-C12)*24-E12 -> 0 | G12: =+IF(C12>0.333333333333333,+(C12-0.333333333333333)*24*60,"0") -> 0 | H12: Feriado: Semana Santa
A13: 46116 | B13: =+A13 -> 46116 | F13: =+(D13-C13)*24-E13 -> 0 | G13: =+IF(C13>0.333333333333333,+(C13-0.333333333333333)*24*60,"0") -> 0
A14: 46117 | B14: =+A14 -> 46117 | F14: =+(D14-C14)*24-E14 -> 0 | G14: =+IF(C14>0.333333333333333,+(C14-0.333333333333333)*24*60,"0") -> 0
A15: 46118 | B15: =+A15 -> 46118 | C15: 0.33333333 | D15: 0.70833333 | E15: 1 | F15: =+(D15-C15)*24-E15 -> 8 | G15: =+IF(C15>0.333333333333333,+(C15-0.333333333333333)*24*60,"0") -> 0
A16: 46119 | B16: =+A16 -> 46119 | C16: 0.33333333 | D16: 0.70833333 | F16: =+(D16-C16)*24-E16 -> 9 | G16: =+IF(C16>0.333333333333333,+(C16-0.333333333333333)*24*60,"0") -> 0
A17: 46120 | B17: =+A17 -> 46120 | C17: 0.33333333 | D17: 0.70833333 | F17: =+(D17-C17)*24-E17 -> 9 | G17: =+IF(C17>0.333333333333333,+(C17-0.333333333333333)*24*60,"0") -> 0
A18: 46121 | B18: =+A18 -> 46121 | C18: 0.42847222 | D18: 0.7125 | E18: 1 | F18: =+(D18-C18)*24-E18 -> 5.8166667 | G18: =+IF(C18>0.333333333333333,+(C18-0.333333333333333)*24*60,"0") -> 137
A19: 46122 | B19: =+A19 -> 46122 | C19: 0.33888889 | D19: 0.70902778 | E19: 1 | F19: =+(D19-C19)*24-E19 -> 7.8833333 | G19: =+IF(C19>0.333333333333333,+(C19-0.333333333333333)*24*60,"0") -> 8
A20: 46123 | B20: =+A20 -> 46123 | F20: =+(D20-C20)*24-E20 -> 0 | G20: =+IF(C20>0.333333333333333,+(C20-0.333333333333333)*24*60,"0") -> 0
A21: 46124 | B21: =+A21 -> 46124 | F21: =+(D21-C21)*24-E21 -> 0 | G21: =+IF(C21>0.333333333333333,+(C21-0.333333333333333)*24*60,"0") -> 0
A22: 46125 | B22: =+A22 -> 46125 | C22: 0.34861111 | D22: 0.78402778 | E22: 1 | F22: =+(D22-C22)*24-E22 -> 9.45 | G22: =+IF(C22>0.333333333333333,+(C22-0.333333333333333)*24*60,"0") -> 22
A23: 46126 | B23: =+A23 -> 46126 | C23: 0.35486111 | D23: 0.73402778 | E23: 1 | F23: =+(D23-C23)*24-E23 -> 8.1 | G23: =+IF(C23>0.333333333333333,+(C23-0.333333333333333)*24*60,"0") -> 31
A24: 46127 | B24: =+A24 -> 46127 | C24: 0.35138889 | D24: 0.73888889 | E24: 1 | F24: =+(D24-C24)*24-E24 -> 8.3 | G24: =+IF(C24>0.333333333333333,+(C24-0.333333333333333)*24*60,"0") -> 26
A25: 46128 | B25: =+A25 -> 46128 | C25: 0.34513889 | D25: 0.71180556 | E25: 1 | F25: =+(D25-C25)*24-E25 -> 7.8 | G25: =+IF(C25>0.333333333333333,+(C25-0.333333333333333)*24*60,"0") -> 17
A26: 46129 | B26: =+A26 -> 46129 | C26: 0.36180556 | D26: 0.7125 | E26: 1 | F26: =+(D26-C26)*24-E26 -> 7.4166667 | G26: =+IF(C26>0.333333333333333,+(C26-0.333333333333333)*24*60,"0") -> 41
A27: 46130 | B27: =+A27 -> 46130 | F27: =+(D27-C27)*24-E27 -> 0 | G27: =+IF(C27>0.333333333333333,+(C27-0.333333333333333)*24*60,"0") -> 0
A28: 46131 | B28: =+A28 -> 46131 | F28: =+(D28-C28)*24-E28 -> 0 | G28: =+IF(C28>0.333333333333333,+(C28-0.333333333333333)*24*60,"0") -> 0
A29: 46132 | B29: =+A29 -> 46132 | C29: 0.34236111 | D29: 0.70833333 | E29: 1 | F29: =+(D29-C29)*24-E29 -> 7.7833333 | G29: =+IF(C29>0.333333333333333,+(C29-0.333333333333333)*24*60,"0") -> 13
A30: 46133 | B30: =+A30 -> 46133 | F30: =+(D30-C30)*24-E30 -> 0 | G30: =+IF(C30>0.333333333333333,+(C30-0.333333333333333)*24*60,"0") -> 0
A31: 46134 | B31: =+A31 -> 46134 | F31: =+(D31-C31)*24-E31 -> 0 | G31: =+IF(C31>0.333333333333333,+(C31-0.333333333333333)*24*60,"0") -> 0
A32: 46135 | B32: =+A32 -> 46135 | F32: =+(D32-C32)*24-E32 -> 0 | G32: =+IF(C32>0.333333333333333,+(C32-0.333333333333333)*24*60,"0") -> 0
A33: 46136 | B33: =+A33 -> 46136 | F33: =+(D33-C33)*24-E33 -> 0 | G33: =+IF(C33>0.333333333333333,+(C33-0.333333333333333)*24*60,"0") -> 0
A34: 46137 | B34: =+A34 -> 46137 | F34: =+(D34-C34)*24-E34 -> 0 | G34: =+IF(C34>0.333333333333333,+(C34-0.333333333333333)*24*60,"0") -> 0
A35: 46138 | B35: =+A35 -> 46138 | F35: =+(D35-C35)*24-E35 -> 0 | G35: =+IF(C35>0.333333333333333,+(C35-0.333333333333333)*24*60,"0") -> 0
A36: 46139 | B36: =+A36 -> 46139 | F36: =+(D36-C36)*24-E36 -> 0 | G36: =+IF(C36>0.333333333333333,+(C36-0.333333333333333)*24*60,"0") -> 0
A37: 46140 | B37: =+A37 -> 46140 | F37: =+(D37-C37)*24-E37 -> 0 | G37: =+IF(C37>0.333333333333333,+(C37-0.333333333333333)*24*60,"0") -> 0
A38: 46141 | B38: =+A38 -> 46141 | F38: =+(D38-C38)*24-E38 -> 0 | G38: =+IF(C38>0.333333333333333,+(C38-0.333333333333333)*24*60,"0") -> 0
A39: 46142 | B39: =+A39 -> 46142 | F39: =+(D39-C39)*24-E39 -> 0 | G39: =+IF(C39>0.333333333333333,+(C39-0.333333333333333)*24*60,"0") -> 0
A40: TOTAL DIAS TRABAJADOS | C40: =+COUNT(C10:C39) -> 11
A41: TOTAL HORAS TRABAJADAS | C41: =SUM(F10:F39) -> 88.55
A42: ATRASOS | C42: =SUM(G10:G39) -> 295

Sheet 4
A2: PLANILLA CONTROL DE ASISTENCIA
A4: ITEM | B4: 4
A5: NOMBRE | B5: OSCAR ROLANDO MENDEZ ROCA FARELL
A6: CARGO | B6: Project Manager Regional CBA
A7: HABER BASICO | B7: 8000 | C7: Bs.
A9: FECHA | B9: DIA | C9: HORA INGRESO | D9: HORA SALIDA | E9: REFRIGERIO | F9: HORAS TRABAJO | G9: ATRASOS MINUTOS | H9: OBSERVACIONES
A10: 46113 | B10: =+A10 -> 46113 | F10: =+(D10-C10)*24-E10 -> 0 | G10: =+IF(C10>0.333333333333333,+(C10-0.333333333333333)*24*60,"0") -> 0
A11: 46114 | B11: =+A11 -> 46114 | F11: =+(D11-C11)*24-E11 -> 0 | G11: =+IF(C11>0.333333333333333,+(C11-0.333333333333333)*24*60,"0") -> 0
A12: 46115 | B12: =+A12 -> 46115 | F12: =+(D12-C12)*24-E12 -> 0 | G12: =+IF(C12>0.333333333333333,+(C12-0.333333333333333)*24*60,"0") -> 0 | H12: Feriado: Semana Santa
A13: 46116 | B13: =+A13 -> 46116 | F13: =+(D13-C13)*24-E13 -> 0 | G13: =+IF(C13>0.333333333333333,+(C13-0.333333333333333)*24*60,"0") -> 0
A14: 46117 | B14: =+A14 -> 46117 | F14: =+(D14-C14)*24-E14 -> 0 | G14: =+IF(C14>0.333333333333333,+(C14-0.333333333333333)*24*60,"0") -> 0
A15: 46118 | B15: =+A15 -> 46118 | F15: =+(D15-C15)*24-E15 -> 0 | G15: =+IF(C15>0.333333333333333,+(C15-0.333333333333333)*24*60,"0") -> 0
A16: 46119 | B16: =+A16 -> 46119 | F16: =+(D16-C16)*24-E16 -> 0 | G16: =+IF(C16>0.333333333333333,+(C16-0.333333333333333)*24*60,"0") -> 0
A17: 46120 | B17: =+A17 -> 46120 | F17: =+(D17-C17)*24-E17 -> 0 | G17: =+IF(C17>0.333333333333333,+(C17-0.333333333333333)*24*60,"0") -> 0
A18: 46121 | B18: =+A18 -> 46121 | F18: =+(D18-C18)*24-E18 -> 0 | G18: =+IF(C18>0.333333333333333,+(C18-0.333333333333333)*24*60,"0") -> 0
A19: 46122 | B19: =+A19 -> 46122 | F19: =+(D19-C19)*24-E19 -> 0 | G19: =+IF(C19>0.333333333333333,+(C19-0.333333333333333)*24*60,"0") -> 0
A20: 46123 | B20: =+A20 -> 46123 | F20: =+(D20-C20)*24-E20 -> 0 | G20: =+IF(C20>0.333333333333333,+(C20-0.333333333333333)*24*60,"0") -> 0
A21: 46124 | B21: =+A21 -> 46124 | F21: =+(D21-C21)*24-E21 -> 0 | G21: =+IF(C21>0.333333333333333,+(C21-0.333333333333333)*24*60,"0") -> 0
A22: 46125 | B22: =+A22 -> 46125 | F22: =+(D22-C22)*24-E22 -> 0 | G22: =+IF(C22>0.333333333333333,+(C22-0.333333333333333)*24*60,"0") -> 0
A23: 46126 | B23: =+A23 -> 46126 | C23: 0.33333333 | D23: 0.75 | E23: 1 | F23: =+(D23-C23)*24-E23 -> 9 | G23: =+IF(C23>0.333333333333333,+(C23-0.333333333333333)*24*60,"0") -> 0
A24: 46127 | B24: =+A24 -> 46127 | C24: 0.35277778 | D24: 0.75277778 | E24: 1 | F24: =+(D24-C24)*24-E24 -> 8.6 | G24: =+IF(C24>0.333333333333333,+(C24-0.333333333333333)*24*60,"0") -> 28
A25: 46128 | B25: =+A25 -> 46128 | C25: 0.34097222 | D25: 0.75555556 | E25: 1 | F25: =+(D25-C25)*24-E25 -> 8.95 | G25: =+IF(C25>0.333333333333333,+(C25-0.333333333333333)*24*60,"0") -> 11
A26: 46129 | B26: =+A26 -> 46129 | C26: 0.32986111 | D26: 0.75555556 | E26: 1 | F26: =+(D26-C26)*24-E26 -> 9.2166667 | G26: =+IF(C26>0.333333333333333,+(C26-0.333333333333333)*24*60,"0") -> 0
A27: 46130 | B27: =+A27 -> 46130 | C27: 0.37152778 | D27: 0.4625 | E27: 1 | F27: =+(D27-C27)*24-E27 -> 1.1833333 | G27: =+IF(C27>0.333333333333333,+(C27-0.333333333333333)*24*60,"0") -> 55
A28: 46131 | B28: =+A28 -> 46131 | F28: =+(D28-C28)*24-E28 -> 0 | G28: =+IF(C28>0.333333333333333,+(C28-0.333333333333333)*24*60,"0") -> 0
A29: 46132 | B29: =+A29 -> 46132 | C29: 0.325 | D29: 0.72708333 | E29: 1 | F29: =+(D29-C29)*24-E29 -> 8.65 | G29: =+IF(C29>0.333333333333333,+(C29-0.333333333333333)*24*60,"0") -> 0
A30: 46133 | B30: =+A30 -> 46133 | F30: =+(D30-C30)*24-E30 -> 0 | G30: =+IF(C30>0.333333333333333,+(C30-0.333333333333333)*24*60,"0") -> 0
A31: 46134 | B31: =+A31 -> 46134 | F31: =+(D31-C31)*24-E31 -> 0 | G31: =+IF(C31>0.333333333333333,+(C31-0.333333333333333)*24*60,"0") -> 0
A32: 46135 | B32: =+A32 -> 46135 | F32: =+(D32-C32)*24-E32 -> 0 | G32: =+IF(C32>0.333333333333333,+(C32-0.333333333333333)*24*60,"0") -> 0
A33: 46136 | B33: =+A33 -> 46136 | F33: =+(D33-C33)*24-E33 -> 0 | G33: =+IF(C33>0.333333333333333,+(C33-0.333333333333333)*24*60,"0") -> 0
A34: 46137 | B34: =+A34 -> 46137 | F34: =+(D34-C34)*24-E34 -> 0 | G34: =+IF(C34>0.333333333333333,+(C34-0.333333333333333)*24*60,"0") -> 0
A35: 46138 | B35: =+A35 -> 46138 | F35: =+(D35-C35)*24-E35 -> 0 | G35: =+IF(C35>0.333333333333333,+(C35-0.333333333333333)*24*60,"0") -> 0
A36: 46139 | B36: =+A36 -> 46139 | F36: =+(D36-C36)*24-E36 -> 0 | G36: =+IF(C36>0.333333333333333,+(C36-0.333333333333333)*24*60,"0") -> 0
A37: 46140 | B37: =+A37 -> 46140 | F37: =+(D37-C37)*24-E37 -> 0 | G37: =+IF(C37>0.333333333333333,+(C37-0.333333333333333)*24*60,"0") -> 0
A38: 46141 | B38: =+A38 -> 46141 | F38: =+(D38-C38)*24-E38 -> 0 | G38: =+IF(C38>0.333333333333333,+(C38-0.333333333333333)*24*60,"0") -> 0
A39: 46142 | B39: =+A39 -> 46142 | F39: =+(D39-C39)*24-E39 -> 0 | G39: =+IF(C39>0.333333333333333,+(C39-0.333333333333333)*24*60,"0") -> 0
A40: TOTAL DIAS TRABAJADOS | C40: =+COUNT(C10:C39) -> 6
A41: TOTAL HORAS TRABAJADAS | C41: =SUM(F10:F39) -> 45.6
A42: ATRASOS | C42: =SUM(G10:G39) -> 94

Sheet 5
A2: PLANILLA CONTROL DE ASISTENCIA
A4: ITEM | B4: 5
A5: NOMBRE | B5: JORGE LUIS ROJAS DÁVILA
A6: CARGO | B6: Supervisor Civil Regional SCZ
A7: HABER BASICO | B7: 9165 | C7: Bs.
A9: FECHA | B9: DIA | C9: HORA INGRESO | D9: HORA SALIDA | E9: REFRIGERIO | F9: HORAS TRABAJO | G9: ATRASOS MINUTOS | H9: OBSERVACIONES
A10: 46113 | B10: =+A10 -> 46113 | C10: 0.33333333 | D10: 0.70833333 | E10: 1 | F10: =+(D10-C10)*24-E10 -> 8 | G10: =+IF(C10>0.333333333333333,+(C10-0.333333333333333)*24*60,"0") -> 0
A11: 46114 | B11: =+A11 -> 46114 | C11: 0.63263889 | D11: 0.70833333 | E11: 1 | F11: =+(D11-C11)*24-E11 -> 0.81666667 | G11: =+IF(C11>0.333333333333333,+(C11-0.333333333333333)*24*60,"0") -> 431
A12: 46115 | B12: =+A12 -> 46115 | F12: =+(D12-C12)*24-E12 -> 0 | G12: =+IF(C12>0.333333333333333,+(C12-0.333333333333333)*24*60,"0") -> 0 | H12: Feriado: Semana Santa
A13: 46116 | B13: =+A13 -> 46116 | F13: =+(D13-C13)*24-E13 -> 0 | G13: =+IF(C13>0.333333333333333,+(C13-0.333333333333333)*24*60,"0") -> 0
A14: 46117 | B14: =+A14 -> 46117 | F14: =+(D14-C14)*24-E14 -> 0 | G14: =+IF(C14>0.333333333333333,+(C14-0.333333333333333)*24*60,"0") -> 0
A15: 46118 | B15: =+A15 -> 46118 | C15: 0.34652778 | D15: 0.77638889 | E15: 1 | F15: =+(D15-C15)*24-E15 -> 9.3166667 | G15: =+IF(C15>0.333333333333333,+(C15-0.333333333333333)*24*60,"0") -> 19
A16: 46119 | B16: =+A16 -> 46119 | C16: 0.34236111 | D16: 0.77638889 | E16: 1 | F16: =+(D16-C16)*24-E16 -> 9.4166667 | G16: =+IF(C16>0.333333333333333,+(C16-0.333333333333333)*24*60,"0") -> 13
A17: 46120 | B17: =+A17 -> 46120 | C17: 0.33888889 | D17: 0.77430556 | E17: 1 | F17: =+(D17-C17)*24-E17 -> 9.45 | G17: =+IF(C17>0.333333333333333,+(C17-0.333333333333333)*24*60,"0") -> 8
A18: 46121 | B18: =+A18 -> 46121 | C18: 0.34166667 | D18: 0.77638889 | E18: 1 | F18: =+(D18-C18)*24-E18 -> 9.4333333 | G18: =+IF(C18>0.333333333333333,+(C18-0.333333333333333)*24*60,"0") -> 12
A19: 46122 | B19: =+A19 -> 46122 | C19: 0.33958333 | D19: 0.77361111 | E19: 1 | F19: =+(D19-C19)*24-E19 -> 9.4166667 | G19: =+IF(C19>0.333333333333333,+(C19-0.333333333333333)*24*60,"0") -> 9
A20: 46123 | B20: =+A20 -> 46123 | F20: =+(D20-C20)*24-E20 -> 0 | G20: =+IF(C20>0.333333333333333,+(C20-0.333333333333333)*24*60,"0") -> 0
A21: 46124 | B21: =+A21 -> 46124 | F21: =+(D21-C21)*24-E21 -> 0 | G21: =+IF(C21>0.333333333333333,+(C21-0.333333333333333)*24*60,"0") -> 0
A22: 46125 | B22: =+A22 -> 46125 | C22: 0.33888889 | D22: 0.77083333 | E22: 1 | F22: =+(D22-C22)*24-E22 -> 9.3666667 | G22: =+IF(C22>0.333333333333333,+(C22-0.333333333333333)*24*60,"0") -> 8
A23: 46126 | B23: =+A23 -> 46126 | C23: 0.33888889 | D23: 0.77361111 | E23: 1 | F23: =+(D23-C23)*24-E23 -> 9.4333333 | G23: =+IF(C23>0.333333333333333,+(C23-0.333333333333333)*24*60,"0") -> 8
A24: 46127 | B24: =+A24 -> 46127 | C24: 0.33958333 | D24: 0.77222222 | E24: 1 | F24: =+(D24-C24)*24-E24 -> 9.3833333 | G24: =+IF(C24>0.333333333333333,+(C24-0.333333333333333)*24*60,"0") -> 9
A25: 46128 | B25: =+A25 -> 46128 | C25: 0.33402778 | D25: 0.77361111 | E25: 1 | F25: =+(D25-C25)*24-E25 -> 9.55 | G25: =+IF(C25>0.333333333333333,+(C25-0.333333333333333)*24*60,"0") -> 1
A26: 46129 | B26: =+A26 -> 46129 | C26: 0.33680556 | D26: 0.77291667 | E26: 1 | F26: =+(D26-C26)*24-E26 -> 9.4666667 | G26: =+IF(C26>0.333333333333333,+(C26-0.333333333333333)*24*60,"0") -> 5
A27: 46130 | B27: =+A27 -> 46130 | F27: =+(D27-C27)*24-E27 -> 0 | G27: =+IF(C27>0.333333333333333,+(C27-0.333333333333333)*24*60,"0") -> 0
A28: 46131 | B28: =+A28 -> 46131 | F28: =+(D28-C28)*24-E28 -> 0 | G28: =+IF(C28>0.333333333333333,+(C28-0.333333333333333)*24*60,"0") -> 0
A29: 46132 | B29: =+A29 -> 46132 | C29: 0.34097222 | D29: 0.77708333 | E29: 1 | F29: =+(D29-C29)*24-E29 -> 9.4666667 | G29: =+IF(C29>0.333333333333333,+(C29-0.333333333333333)*24*60,"0") -> 11
A30: 46133 | B30: =+A30 -> 46133 | F30: =+(D30-C30)*24-E30 -> 0 | G30: =+IF(C30>0.333333333333333,+(C30-0.333333333333333)*24*60,"0") -> 0
A31: 46134 | B31: =+A31 -> 46134 | F31: =+(D31-C31)*24-E31 -> 0 | G31: =+IF(C31>0.333333333333333,+(C31-0.333333333333333)*24*60,"0") -> 0
A32: 46135 | B32: =+A32 -> 46135 | F32: =+(D32-C32)*24-E32 -> 0 | G32: =+IF(C32>0.333333333333333,+(C32-0.333333333333333)*24*60,"0") -> 0
A33: 46136 | B33: =+A33 -> 46136 | F33: =+(D33-C33)*24-E33 -> 0 | G33: =+IF(C33>0.333333333333333,+(C33-0.333333333333333)*24*60,"0") -> 0
A34: 46137 | B34: =+A34 -> 46137 | F34: =+(D34-C34)*24-E34 -> 0 | G34: =+IF(C34>0.333333333333333,+(C34-0.333333333333333)*24*60,"0") -> 0
A35: 46138 | B35: =+A35 -> 46138 | F35: =+(D35-C35)*24-E35 -> 0 | G35: =+IF(C35>0.333333333333333,+(C35-0.333333333333333)*24*60,"0") -> 0
A36: 46139 | B36: =+A36 -> 46139 | F36: =+(D36-C36)*24-E36 -> 0 | G36: =+IF(C36>0.333333333333333,+(C36-0.333333333333333)*24*60,"0") -> 0
A37: 46140 | B37: =+A37 -> 46140 | F37: =+(D37-C37)*24-E37 -> 0 | G37: =+IF(C37>0.333333333333333,+(C37-0.333333333333333)*24*60,"0") -> 0
A38: 46141 | B38: =+A38 -> 46141 | F38: =+(D38-C38)*24-E38 -> 0 | G38: =+IF(C38>0.333333333333333,+(C38-0.333333333333333)*24*60,"0") -> 0
A39: 46142 | B39: =+A39 -> 46142 | F39: =+(D39-C39)*24-E39 -> 0 | G39: =+IF(C39>0.333333333333333,+(C39-0.333333333333333)*24*60,"0") -> 0
A40: TOTAL DIAS TRABAJADOS | C40: =+COUNT(C10:C39) -> 13
A41: TOTAL HORAS TRABAJADAS | C41: =SUM(F10:F39) -> 112.51667
A42: ATRASOS | C42: =SUM(G10:G39) -> 534

Sheet 6
A2: PLANILLA CONTROL DE ASISTENCIA
A4: ITEM | B4: 6
A5: NOMBRE | B5: OSCAR FABIAN QUIROGA TAMAYO
A6: CARGO | B6: Supervisor Civil Regional CBA
A7: HABER BASICO | B7: 8485 | C7: Bs.
A9: FECHA | B9: DIA | C9: HORA INGRESO | D9: HORA SALIDA | E9: REFRIGERIO | F9: HORAS TRABAJO | G9: ATRASOS MINUTOS | H9: OBSERVACIONES
A10: 46113 | B10: =+A10 -> 46113 | C10: 0.33333333 | D10: 0.70833333 | E10: 1 | F10: =+(D10-C10)*24-E10 -> 8 | G10: =+IF(C10>0.333333333333333,+(C10-0.333333333333333)*24*60,"0") -> 0
A11: 46114 | B11: =+A11 -> 46114 | C11: 0.33333333 | D11: 0.70833333 | E11: 1 | F11: =+(D11-C11)*24-E11 -> 8 | G11: =+IF(C11>0.333333333333333,+(C11-0.333333333333333)*24*60,"0") -> 0
A12: 46115 | B12: =+A12 -> 46115 | F12: =+(D12-C12)*24-E12 -> 0 | G12: =+IF(C12>0.333333333333333,+(C12-0.333333333333333)*24*60,"0") -> 0 | H12: Feriado: Semana Santa
A13: 46116 | B13: =+A13 -> 46116 | F13: =+(D13-C13)*24-E13 -> 0 | G13: =+IF(C13>0.333333333333333,+(C13-0.333333333333333)*24*60,"0") -> 0
A14: 46117 | B14: =+A14 -> 46117 | F14: =+(D14-C14)*24-E14 -> 0 | G14: =+IF(C14>0.333333333333333,+(C14-0.333333333333333)*24*60,"0") -> 0
A15: 46118 | B15: =+A15 -> 46118 | C15: 0.33333333 | D15: 0.70833333 | E15: 1 | F15: =+(D15-C15)*24-E15 -> 8 | G15: =+IF(C15>0.333333333333333,+(C15-0.333333333333333)*24*60,"0") -> 0
A16: 46119 | B16: =+A16 -> 46119 | C16: 0.33333333 | D16: 0.70833333 | E16: 1 | F16: =+(D16-C16)*24-E16 -> 8 | G16: =+IF(C16>0.333333333333333,+(C16-0.333333333333333)*24*60,"0") -> 0
A17: 46120 | B17: =+A17 -> 46120 | C17: 0.33333333 | D17: 0.70833333 | E17: 1 | F17: =+(D17-C17)*24-E17 -> 8 | G17: =+IF(C17>0.333333333333333,+(C17-0.333333333333333)*24*60,"0") -> 0
A18: 46121 | B18: =+A18 -> 46121 | C18: 0.34652778 | D18: 0.76458333 | E18: 1 | F18: =+(D18-C18)*24-E18 -> 9.0333333 | G18: =+IF(C18>0.333333333333333,+(C18-0.333333333333333)*24*60,"0") -> 19
A19: 46122 | B19: =+A19 -> 46122 | C19: 0.34513889 | D19: 0.76875 | E19: 1 | F19: =+(D19-C19)*24-E19 -> 9.1666667 | G19: =+IF(C19>0.333333333333333,+(C19-0.333333333333333)*24*60,"0") -> 17
A20: 46123 | B20: =+A20 -> 46123 | F20: =+(D20-C20)*24-E20 -> 0 | G20: =+IF(C20>0.333333333333333,+(C20-0.333333333333333)*24*60,"0") -> 0
A21: 46124 | B21: =+A21 -> 46124 | F21: =+(D21-C21)*24-E21 -> 0 | G21: =+IF(C21>0.333333333333333,+(C21-0.333333333333333)*24*60,"0") -> 0
A22: 46125 | B22: =+A22 -> 46125 | C22: 0.34652778 | D22: 0.78541667 | E22: 1 | F22: =+(D22-C22)*24-E22 -> 9.5333333 | G22: =+IF(C22>0.333333333333333,+(C22-0.333333333333333)*24*60,"0") -> 19
A23: 46126 | B23: =+A23 -> 46126 | C23: 0.35069444 | D23: 0.77986111 | E23: 1 | F23: =+(D23-C23)*24-E23 -> 9.3 | G23: =+IF(C23>0.333333333333333,+(C23-0.333333333333333)*24*60,"0") -> 25
A24: 46127 | B24: =+A24 -> 46127 | C24: 0.35972222 | D24: 0.80347222 | E24: 1 | F24: =+(D24-C24)*24-E24 -> 9.65 | G24: =+IF(C24>0.333333333333333,+(C24-0.333333333333333)*24*60,"0") -> 38
A25: 46128 | B25: =+A25 -> 46128 | C25: 0.33402778 | D25: 0.76875 | E25: 1 | F25: =+(D25-C25)*24-E25 -> 9.4333333 | G25: =+IF(C25>0.333333333333333,+(C25-0.333333333333333)*24*60,"0") -> 1
A26: 46129 | B26: =+A26 -> 46129 | C26: 0.4 | D26: 0.83333333 | E26: 1 | F26: =+(D26-C26)*24-E26 -> 9.4 | G26: =+IF(C26>0.333333333333333,+(C26-0.333333333333333)*24*60,"0") -> 96
A27: 46130 | B27: =+A27 -> 46130 | C27: 0.38819444 | D27: 0.54236111 | E27: 1 | F27: =+(D27-C27)*24-E27 -> 2.7 | G27: =+IF(C27>0.333333333333333,+(C27-0.333333333333333)*24*60,"0") -> 79
A28: 46131 | B28: =+A28 -> 46131 | F28: =+(D28-C28)*24-E28 -> 0 | G28: =+IF(C28>0.333333333333333,+(C28-0.333333333333333)*24*60,"0") -> 0
A29: 46132 | B29: =+A29 -> 46132 | C29: 0.34305556 | D29: 0.85 | E29: 1 | F29: =+(D29-C29)*24-E29 -> 11.166667 | G29: =+IF(C29>0.333333333333333,+(C29-0.333333333333333)*24*60,"0") -> 14
A30: 46133 | B30: =+A30 -> 46133 | F30: =+(D30-C30)*24-E30 -> 0 | G30: =+IF(C30>0.333333333333333,+(C30-0.333333333333333)*24*60,"0") -> 0
A31: 46134 | B31: =+A31 -> 46134 | F31: =+(D31-C31)*24-E31 -> 0 | G31: =+IF(C31>0.333333333333333,+(C31-0.333333333333333)*24*60,"0") -> 0
A32: 46135 | B32: =+A32 -> 46135 | F32: =+(D32-C32)*24-E32 -> 0 | G32: =+IF(C32>0.333333333333333,+(C32-0.333333333333333)*24*60,"0") -> 0
A33: 46136 | B33: =+A33 -> 46136 | F33: =+(D33-C33)*24-E33 -> 0 | G33: =+IF(C33>0.333333333333333,+(C33-0.333333333333333)*24*60,"0") -> 0
A34: 46137 | B34: =+A34 -> 46137 | F34: =+(D34-C34)*24-E34 -> 0 | G34: =+IF(C34>0.333333333333333,+(C34-0.333333333333333)*24*60,"0") -> 0
A35: 46138 | B35: =+A35 -> 46138 | F35: =+(D35-C35)*24-E35 -> 0 | G35: =+IF(C35>0.333333333333333,+(C35-0.333333333333333)*24*60,"0") -> 0
A36: 46139 | B36: =+A36 -> 46139 | F36: =+(D36-C36)*24-E36 -> 0 | G36: =+IF(C36>0.333333333333333,+(C36-0.333333333333333)*24*60,"0") -> 0
A37: 46140 | B37: =+A37 -> 46140 | F37: =+(D37-C37)*24-E37 -> 0 | G37: =+IF(C37>0.333333333333333,+(C37-0.333333333333333)*24*60,"0") -> 0
A38: 46141 | B38: =+A38 -> 46141 | F38: =+(D38-C38)*24-E38 -> 0 | G38: =+IF(C38>0.333333333333333,+(C38-0.333333333333333)*24*60,"0") -> 0
A39: 46142 | B39: =+A39 -> 46142 | F39: =+(D39-C39)*24-E39 -> 0 | G39: =+IF(C39>0.333333333333333,+(C39-0.333333333333333)*24*60,"0") -> 0
A40: TOTAL DIAS TRABAJADOS | C40: =+COUNT(C10:C39) -> 14
A41: TOTAL HORAS TRABAJADAS | C41: =SUM(F10:F39) -> 119.38333
A42: ATRASOS | C42: =SUM(G10:G39) -> 308

Sheet 7
A2: PLANILLA CONTROL DE ASISTENCIA
A4: ITEM | B4: 7
A5: NOMBRE | B5: MARTIN EDUARDO VELIZ AREVALO
A6: CARGO | B6: Supervisor Civil Regional LPZ
A7: HABER BASICO | B7: 8485 | C7: Bs.
A9: FECHA | B9: DIA | C9: HORA INGRESO | D9: HORA SALIDA | E9: REFRIGERIO | F9: HORAS TRABAJO | G9: ATRASOS MINUTOS | H9: OBSERVACIONES
A10: 46113 | B10: =+A10 -> 46113 | F10: =+(D10-C10)*24-E10 -> 0 | G10: =+IF(C10>0.333333333333333,+(C10-0.333333333333333)*24*60,"0") -> 0
A11: 46114 | B11: =+A11 -> 46114 | F11: =+(D11-C11)*24-E11 -> 0 | G11: =+IF(C11>0.333333333333333,+(C11-0.333333333333333)*24*60,"0") -> 0
A12: 46115 | B12: =+A12 -> 46115 | F12: =+(D12-C12)*24-E12 -> 0 | G12: =+IF(C12>0.333333333333333,+(C12-0.333333333333333)*24*60,"0") -> 0 | H12: Feriado: Semana Santa
A13: 46116 | B13: =+A13 -> 46116 | F13: =+(D13-C13)*24-E13 -> 0 | G13: =+IF(C13>0.333333333333333,+(C13-0.333333333333333)*24*60,"0") -> 0
A14: 46117 | B14: =+A14 -> 46117 | F14: =+(D14-C14)*24-E14 -> 0 | G14: =+IF(C14>0.333333333333333,+(C14-0.333333333333333)*24*60,"0") -> 0
A15: 46118 | B15: =+A15 -> 46118 | F15: =+(D15-C15)*24-E15 -> 0 | G15: =+IF(C15>0.333333333333333,+(C15-0.333333333333333)*24*60,"0") -> 0
A16: 46119 | B16: =+A16 -> 46119 | C16: 0.33333333 | D16: 0.70833333 | E16: 1 | F16: =+(D16-C16)*24-E16 -> 8 | G16: =+IF(C16>0.333333333333333,+(C16-0.333333333333333)*24*60,"0") -> 0
A17: 46120 | B17: =+A17 -> 46120 | C17: 0.33333333 | D17: 0.70833333 | E17: 1 | F17: =+(D17-C17)*24-E17 -> 8 | G17: =+IF(C17>0.333333333333333,+(C17-0.333333333333333)*24*60,"0") -> 0
A18: 46121 | B18: =+A18 -> 46121 | C18: 0.33333333 | D18: 0.70833333 | E18: 1 | F18: =+(D18-C18)*24-E18 -> 8 | G18: =+IF(C18>0.333333333333333,+(C18-0.333333333333333)*24*60,"0") -> 0
A19: 46122 | B19: =+A19 -> 46122 | C19: 0.33333333 | D19: 0.71180556 | E19: 1 | F19: =+(D19-C19)*24-E19 -> 8.0833333 | G19: =+IF(C19>0.333333333333333,+(C19-0.333333333333333)*24*60,"0") -> 0
A20: 46123 | B20: =+A20 -> 46123 | F20: =+(D20-C20)*24-E20 -> 0 | G20: =+IF(C20>0.333333333333333,+(C20-0.333333333333333)*24*60,"0") -> 0
A21: 46124 | B21: =+A21 -> 46124 | F21: =+(D21-C21)*24-E21 -> 0 | G21: =+IF(C21>0.333333333333333,+(C21-0.333333333333333)*24*60,"0") -> 0
A22: 46125 | B22: =+A22 -> 46125 | C22: 0.46805556 | D22: 0.73194444 | E22: 1 | F22: =+(D22-C22)*24-E22 -> 5.3333333 | G22: =+IF(C22>0.333333333333333,+(C22-0.333333333333333)*24*60,"0") -> 194
A23: 46126 | B23: =+A23 -> 46126 | C23: 0.34930556 | D23: 0.72847222 | E23: 1 | F23: =+(D23-C23)*24-E23 -> 8.1 | G23: =+IF(C23>0.333333333333333,+(C23-0.333333333333333)*24*60,"0") -> 23
A24: 46127 | B24: =+A24 -> 46127 | C24: 0.35277778 | D24: 0.74097222 | E24: 1 | F24: =+(D24-C24)*24-E24 -> 8.3166667 | G24: =+IF(C24>0.333333333333333,+(C24-0.333333333333333)*24*60,"0") -> 28
A25: 46128 | B25: =+A25 -> 46128 | C25: 0.35416667 | D25: 0.79097222 | E25: 1 | F25: =+(D25-C25)*24-E25 -> 9.4833333 | G25: =+IF(C25>0.333333333333333,+(C25-0.333333333333333)*24*60,"0") -> 30
A26: 46129 | B26: =+A26 -> 46129 | C26: 0.35069444 | D26: 0.81180556 | E26: 1 | F26: =+(D26-C26)*24-E26 -> 10.066667 | G26: =+IF(C26>0.333333333333333,+(C26-0.333333333333333)*24*60,"0") -> 25
A27: 46130 | B27: =+A27 -> 46130 | F27: =+(D27-C27)*24-E27 -> 0 | G27: =+IF(C27>0.333333333333333,+(C27-0.333333333333333)*24*60,"0") -> 0
A28: 46131 | B28: =+A28 -> 46131 | F28: =+(D28-C28)*24-E28 -> 0 | G28: =+IF(C28>0.333333333333333,+(C28-0.333333333333333)*24*60,"0") -> 0
A29: 46132 | B29: =+A29 -> 46132 | C29: 0.34583333 | D29: 0.70833333 | E29: 1 | F29: =+(D29-C29)*24-E29 -> 7.7 | G29: =+IF(C29>0.333333333333333,+(C29-0.333333333333333)*24*60,"0") -> 18
A30: 46133 | B30: =+A30 -> 46133 | F30: =+(D30-C30)*24-E30 -> 0 | G30: =+IF(C30>0.333333333333333,+(C30-0.333333333333333)*24*60,"0") -> 0
A31: 46134 | B31: =+A31 -> 46134 | F31: =+(D31-C31)*24-E31 -> 0 | G31: =+IF(C31>0.333333333333333,+(C31-0.333333333333333)*24*60,"0") -> 0
A32: 46135 | B32: =+A32 -> 46135 | F32: =+(D32-C32)*24-E32 -> 0 | G32: =+IF(C32>0.333333333333333,+(C32-0.333333333333333)*24*60,"0") -> 0
A33: 46136 | B33: =+A33 -> 46136 | F33: =+(D33-C33)*24-E33 -> 0 | G33: =+IF(C33>0.333333333333333,+(C33-0.333333333333333)*24*60,"0") -> 0
A34: 46137 | B34: =+A34 -> 46137 | F34: =+(D34-C34)*24-E34 -> 0 | G34: =+IF(C34>0.333333333333333,+(C34-0.333333333333333)*24*60,"0") -> 0
A35: 46138 | B35: =+A35 -> 46138 | F35: =+(D35-C35)*24-E35 -> 0 | G35: =+IF(C35>0.333333333333333,+(C35-0.333333333333333)*24*60,"0") -> 0
A36: 46139 | B36: =+A36 -> 46139 | F36: =+(D36-C36)*24-E36 -> 0 | G36: =+IF(C36>0.333333333333333,+(C36-0.333333333333333)*24*60,"0") -> 0
A37: 46140 | B37: =+A37 -> 46140 | F37: =+(D37-C37)*24-E37 -> 0 | G37: =+IF(C37>0.333333333333333,+(C37-0.333333333333333)*24*60,"0") -> 0
A38: 46141 | B38: =+A38 -> 46141 | F38: =+(D38-C38)*24-E38 -> 0 | G38: =+IF(C38>0.333333333333333,+(C38-0.333333333333333)*24*60,"0") -> 0
A39: 46142 | B39: =+A39 -> 46142 | F39: =+(D39-C39)*24-E39 -> 0 | G39: =+IF(C39>0.333333333333333,+(C39-0.333333333333333)*24*60,"0") -> 0
A40: TOTAL DIAS TRABAJADOS | C40: =+COUNT(C10:C39) -> 10
A41: TOTAL HORAS TRABAJADAS | C41: =SUM(F10:F39) -> 81.083333
A42: ATRASOS | C42: =SUM(G10:G39) -> 318

Sheet 8
A2: PLANILLA CONTROL DE ASISTENCIA
A4: ITEM | B4: 8
A5: NOMBRE | B5: RAÚL RAIMUNDO PARRAGA ANTEZANA
A6: CARGO | B6: Supervisor Eléctrico Regional
A7: HABER BASICO | B7: 9165 | C7: Bs.
A9: FECHA | B9: DIA | C9: HORA INGRESO | D9: HORA SALIDA | E9: REFRIGERIO | F9: HORAS TRABAJO | G9: ATRASOS MINUTOS | H9: OBSERVACIONES
A10: 46113 | B10: =+A10 -> 46113 | C10: 0.33333333 | D10: 0.70833333 | E10: 1 | F10: =+(D10-C10)*24-E10 -> 8 | G10: =+IF(C10>0.333333333333333,+(C10-0.333333333333333)*24*60,"0") -> 0
A11: 46114 | B11: =+A11 -> 46114 | C11: 0.33333333 | D11: 0.76527778 | E11: 1 | F11: =+(D11-C11)*24-E11 -> 9.3666667 | G11: =+IF(C11>0.333333333333333,+(C11-0.333333333333333)*24*60,"0") -> 0
A12: 46115 | B12: =+A12 -> 46115 | F12: =+(D12-C12)*24-E12 -> 0 | G12: =+IF(C12>0.333333333333333,+(C12-0.333333333333333)*24*60,"0") -> 0 | H12: Feriado: Semana Santa
A13: 46116 | B13: =+A13 -> 46116 | F13: =+(D13-C13)*24-E13 -> 0 | G13: =+IF(C13>0.333333333333333,+(C13-0.333333333333333)*24*60,"0") -> 0
A14: 46117 | B14: =+A14 -> 46117 | F14: =+(D14-C14)*24-E14 -> 0 | G14: =+IF(C14>0.333333333333333,+(C14-0.333333333333333)*24*60,"0") -> 0
A15: 46118 | B15: =+A15 -> 46118 | C15: 0.35902778 | D15: 0.78333333 | E15: 1 | F15: =+(D15-C15)*24-E15 -> 9.1833333 | G15: =+IF(C15>0.333333333333333,+(C15-0.333333333333333)*24*60,"0") -> 37
A16: 46119 | B16: =+A16 -> 46119 | C16: 0.34652778 | D16: 0.78472222 | E16: 1 | F16: =+(D16-C16)*24-E16 -> 9.5166667 | G16: =+IF(C16>0.333333333333333,+(C16-0.333333333333333)*24*60,"0") -> 19
A17: 46120 | B17: =+A17 -> 46120 | C17: 0.33888889 | D17: 0.7875 | E17: 1 | F17: =+(D17-C17)*24-E17 -> 9.7666667 | G17: =+IF(C17>0.333333333333333,+(C17-0.333333333333333)*24*60,"0") -> 8
A18: 46121 | B18: =+A18 -> 46121 | C18: 0.34583333 | D18: 0.78819444 | E18: 1 | F18: =+(D18-C18)*24-E18 -> 9.6166667 | G18: =+IF(C18>0.333333333333333,+(C18-0.333333333333333)*24*60,"0") -> 18
A19: 46122 | B19: =+A19 -> 46122 | C19: 0.34652778 | D19: 0.79166667 | E19: 1 | F19: =+(D19-C19)*24-E19 -> 9.6833333 | G19: =+IF(C19>0.333333333333333,+(C19-0.333333333333333)*24*60,"0") -> 19
A20: 46123 | B20: =+A20 -> 46123 | F20: =+(D20-C20)*24-E20 -> 0 | G20: =+IF(C20>0.333333333333333,+(C20-0.333333333333333)*24*60,"0") -> 0
A21: 46124 | B21: =+A21 -> 46124 | F21: =+(D21-C21)*24-E21 -> 0 | G21: =+IF(C21>0.333333333333333,+(C21-0.333333333333333)*24*60,"0") -> 0
A22: 46125 | B22: =+A22 -> 46125 | C22: 0.34652778 | D22: 0.75208333 | E22: 1 | F22: =+(D22-C22)*24-E22 -> 8.7333333 | G22: =+IF(C22>0.333333333333333,+(C22-0.333333333333333)*24*60,"0") -> 19
A23: 46126 | B23: =+A23 -> 46126 | C23: 0.34791667 | D23: 0.34722222 | E23: 1 | F23: =+(D23-C23)*24-E23 -> -1.0166667 | G23: =+IF(C23>0.333333333333333,+(C23-0.333333333333333)*24*60,"0") -> 21
A24: 46127 | B24: =+A24 -> 46127 | C24: 0.34722222 | D24: 0.77291667 | E24: 1 | F24: =+(D24-C24)*24-E24 -> 9.2166667 | G24: =+IF(C24>0.333333333333333,+(C24-0.333333333333333)*24*60,"0") -> 20
A25: 46128 | B25: =+A25 -> 46128 | C25: 0.33888889 | D25: 0.78194444 | E25: 1 | F25: =+(D25-C25)*24-E25 -> 9.6333333 | G25: =+IF(C25>0.333333333333333,+(C25-0.333333333333333)*24*60,"0") -> 8
A26: 46129 | B26: =+A26 -> 46129 | C26: 0.35277778 | D26: 0.79097222 | E26: 1 | F26: =+(D26-C26)*24-E26 -> 9.5166667 | G26: =+IF(C26>0.333333333333333,+(C26-0.333333333333333)*24*60,"0") -> 28
A27: 46130 | B27: =+A27 -> 46130 | F27: =+(D27-C27)*24-E27 -> 0 | G27: =+IF(C27>0.333333333333333,+(C27-0.333333333333333)*24*60,"0") -> 0
A28: 46131 | B28: =+A28 -> 46131 | F28: =+(D28-C28)*24-E28 -> 0 | G28: =+IF(C28>0.333333333333333,+(C28-0.333333333333333)*24*60,"0") -> 0
A29: 46132 | B29: =+A29 -> 46132 | C29: 0.34930556 | D29: 0.78125 | E29: 1 | F29: =+(D29-C29)*24-E29 -> 9.3666667 | G29: =+IF(C29>0.333333333333333,+(C29-0.333333333333333)*24*60,"0") -> 23
A30: 46133 | B30: =+A30 -> 46133 | F30: =+(D30-C30)*24-E30 -> 0 | G30: =+IF(C30>0.333333333333333,+(C30-0.333333333333333)*24*60,"0") -> 0
A31: 46134 | B31: =+A31 -> 46134 | F31: =+(D31-C31)*24-E31 -> 0 | G31: =+IF(C31>0.333333333333333,+(C31-0.333333333333333)*24*60,"0") -> 0
A32: 46135 | B32: =+A32 -> 46135 | F32: =+(D32-C32)*24-E32 -> 0 | G32: =+IF(C32>0.333333333333333,+(C32-0.333333333333333)*24*60,"0") -> 0
A33: 46136 | B33: =+A33 -> 46136 | F33: =+(D33-C33)*24-E33 -> 0 | G33: =+IF(C33>0.333333333333333,+(C33-0.333333333333333)*24*60,"0") -> 0
A34: 46137 | B34: =+A34 -> 46137 | F34: =+(D34-C34)*24-E34 -> 0 | G34: =+IF(C34>0.333333333333333,+(C34-0.333333333333333)*24*60,"0") -> 0
A35: 46138 | B35: =+A35 -> 46138 | F35: =+(D35-C35)*24-E35 -> 0 | G35: =+IF(C35>0.333333333333333,+(C35-0.333333333333333)*24*60,"0") -> 0
A36: 46139 | B36: =+A36 -> 46139 | F36: =+(D36-C36)*24-E36 -> 0 | G36: =+IF(C36>0.333333333333333,+(C36-0.333333333333333)*24*60,"0") -> 0
A37: 46140 | B37: =+A37 -> 46140 | F37: =+(D37-C37)*24-E37 -> 0 | G37: =+IF(C37>0.333333333333333,+(C37-0.333333333333333)*24*60,"0") -> 0
A38: 46141 | B38: =+A38 -> 46141 | F38: =+(D38-C38)*24-E38 -> 0 | G38: =+IF(C38>0.333333333333333,+(C38-0.333333333333333)*24*60,"0") -> 0
A39: 46142 | B39: =+A39 -> 46142 | F39: =+(D39-C39)*24-E39 -> 0 | G39: =+IF(C39>0.333333333333333,+(C39-0.333333333333333)*24*60,"0") -> 0
A40: TOTAL DIAS TRABAJADOS | C40: =+COUNT(C10:C39) -> 13
A41: TOTAL HORAS TRABAJADAS | C41: =SUM(F10:F39) -> 110.58333
A42: ATRASOS | C42: =SUM(G10:G39) -> 220

Sheet 9
A2: PLANILLA CONTROL DE ASISTENCIA
A4: ITEM | B4: 9
A5: NOMBRE | B5: ABRAHAM QUENA CABRERA
A6: CARGO | B6: Supervisor Mecánico Regional
A7: HABER BASICO | B7: 9165 | C7: Bs.
A9: FECHA | B9: DIA | C9: HORA INGRESO | D9: HORA SALIDA | E9: REFRIGERIO | F9: HORAS TRABAJO | G9: ATRASOS MINUTOS | H9: OBSERVACIONES
A10: 46113 | B10: =+A10 -> 46113 | C10: 0.33333333 | D10: 0.70833333 | E10: 1 | F10: =+(D10-C10)*24-E10 -> 8 | G10: =+IF(C10>0.333333333333333,+(C10-0.333333333333333)*24*60,"0") -> 0
A11: 46114 | B11: =+A11 -> 46114 | C11: 0.33333333 | D11: 0.70833333 | E11: 1 | F11: =+(D11-C11)*24-E11 -> 8 | G11: =+IF(C11>0.333333333333333,+(C11-0.333333333333333)*24*60,"0") -> 0
A12: 46115 | B12: =+A12 -> 46115 | F12: =+(D12-C12)*24-E12 -> 0 | G12: =+IF(C12>0.333333333333333,+(C12-0.333333333333333)*24*60,"0") -> 0 | H12: Feriado: Semana Santa
A13: 46116 | B13: =+A13 -> 46116 | F13: =+(D13-C13)*24-E13 -> 0 | G13: =+IF(C13>0.333333333333333,+(C13-0.333333333333333)*24*60,"0") -> 0
A14: 46117 | B14: =+A14 -> 46117 | F14: =+(D14-C14)*24-E14 -> 0 | G14: =+IF(C14>0.333333333333333,+(C14-0.333333333333333)*24*60,"0") -> 0
A15: 46118 | B15: =+A15 -> 46118 | C15: 0.44236111 | D15: 0.78472222 | E15: 1 | F15: =+(D15-C15)*24-E15 -> 7.2166667 | G15: =+IF(C15>0.333333333333333,+(C15-0.333333333333333)*24*60,"0") -> 157
A16: 46119 | B16: =+A16 -> 46119 | C16: 0.33819444 | D16: 0.78472222 | E16: 1 | F16: =+(D16-C16)*24-E16 -> 9.7166667 | G16: =+IF(C16>0.333333333333333,+(C16-0.333333333333333)*24*60,"0") -> 7
A17: 46120 | B17: =+A17 -> 46120 | C17: 0.34236111 | D17: 0.80069444 | E17: 1 | F17: =+(D17-C17)*24-E17 -> 10 | G17: =+IF(C17>0.333333333333333,+(C17-0.333333333333333)*24*60,"0") -> 13
A18: 46121 | B18: =+A18 -> 46121 | C18: 0.34930556 | D18: 0.79930556 | E18: 1 | F18: =+(D18-C18)*24-E18 -> 9.8 | G18: =+IF(C18>0.333333333333333,+(C18-0.333333333333333)*24*60,"0") -> 23
A19: 46122 | B19: =+A19 -> 46122 | C19: 0.37569444 | D19: 0.79791667 | E19: 1 | F19: =+(D19-C19)*24-E19 -> 9.1333333 | G19: =+IF(C19>0.333333333333333,+(C19-0.333333333333333)*24*60,"0") -> 61
A20: 46123 | B20: =+A20 -> 46123 | F20: =+(D20-C20)*24-E20 -> 0 | G20: =+IF(C20>0.333333333333333,+(C20-0.333333333333333)*24*60,"0") -> 0
A21: 46124 | B21: =+A21 -> 46124 | F21: =+(D21-C21)*24-E21 -> 0 | G21: =+IF(C21>0.333333333333333,+(C21-0.333333333333333)*24*60,"0") -> 0
A22: 46125 | B22: =+A22 -> 46125 | C22: 0.34652778 | D22: 0.775 | E22: 1 | F22: =+(D22-C22)*24-E22 -> 9.2833333 | G22: =+IF(C22>0.333333333333333,+(C22-0.333333333333333)*24*60,"0") -> 19
A23: 46126 | B23: =+A23 -> 46126 | C23: 0.34166667 | D23: 0.79027778 | E23: 1 | F23: =+(D23-C23)*24-E23 -> 9.7666667 | G23: =+IF(C23>0.333333333333333,+(C23-0.333333333333333)*24*60,"0") -> 12
A24: 46127 | B24: =+A24 -> 46127 | C24: 0.34583333 | D24: 0.78263889 | E24: 1 | F24: =+(D24-C24)*24-E24 -> 9.4833333 | G24: =+IF(C24>0.333333333333333,+(C24-0.333333333333333)*24*60,"0") -> 18
A25: 46128 | B25: =+A25 -> 46128 | C25: 0.34513889 | D25: 0.79375 | E25: 1 | F25: =+(D25-C25)*24-E25 -> 9.7666667 | G25: =+IF(C25>0.333333333333333,+(C25-0.333333333333333)*24*60,"0") -> 17
A26: 46129 | B26: =+A26 -> 46129 | C26: 0.34444444 | D26: 0.80416667 | E26: 1 | F26: =+(D26-C26)*24-E26 -> 10.033333 | G26: =+IF(C26>0.333333333333333,+(C26-0.333333333333333)*24*60,"0") -> 16
A27: 46130 | B27: =+A27 -> 46130 | F27: =+(D27-C27)*24-E27 -> 0 | G27: =+IF(C27>0.333333333333333,+(C27-0.333333333333333)*24*60,"0") -> 0
A28: 46131 | B28: =+A28 -> 46131 | F28: =+(D28-C28)*24-E28 -> 0 | G28: =+IF(C28>0.333333333333333,+(C28-0.333333333333333)*24*60,"0") -> 0
A29: 46132 | B29: =+A29 -> 46132 | C29: 0.35486111 | D29: 0.78819444 | E29: 1 | F29: =+(D29-C29)*24-E29 -> 9.4 | G29: =+IF(C29>0.333333333333333,+(C29-0.333333333333333)*24*60,"0") -> 31
A30: 46133 | B30: =+A30 -> 46133 | F30: =+(D30-C30)*24-E30 -> 0 | G30: =+IF(C30>0.333333333333333,+(C30-0.333333333333333)*24*60,"0") -> 0
A31: 46134 | B31: =+A31 -> 46134 | F31: =+(D31-C31)*24-E31 -> 0 | G31: =+IF(C31>0.333333333333333,+(C31-0.333333333333333)*24*60,"0") -> 0
A32: 46135 | B32: =+A32 -> 46135 | F32: =+(D32-C32)*24-E32 -> 0 | G32: =+IF(C32>0.333333333333333,+(C32-0.333333333333333)*24*60,"0") -> 0
A33: 46136 | B33: =+A33 -> 46136 | F33: =+(D33-C33)*24-E33 -> 0 | G33: =+IF(C33>0.333333333333333,+(C33-0.333333333333333)*24*60,"0") -> 0
A34: 46137 | B34: =+A34 -> 46137 | F34: =+(D34-C34)*24-E34 -> 0 | G34: =+IF(C34>0.333333333333333,+(C34-0.333333333333333)*24*60,"0") -> 0
A35: 46138 | B35: =+A35 -> 46138 | F35: =+(D35-C35)*24-E35 -> 0 | G35: =+IF(C35>0.333333333333333,+(C35-0.333333333333333)*24*60,"0") -> 0
A36: 46139 | B36: =+A36 -> 46139 | F36: =+(D36-C36)*24-E36 -> 0 | G36: =+IF(C36>0.333333333333333,+(C36-0.333333333333333)*24*60,"0") -> 0
A37: 46140 | B37: =+A37 -> 46140 | F37: =+(D37-C37)*24-E37 -> 0 | G37: =+IF(C37>0.333333333333333,+(C37-0.333333333333333)*24*60,"0") -> 0
A38: 46141 | B38: =+A38 -> 46141 | F38: =+(D38-C38)*24-E38 -> 0 | G38: =+IF(C38>0.333333333333333,+(C38-0.333333333333333)*24*60,"0") -> 0
A39: 46142 | B39: =+A39 -> 46142 | F39: =+(D39-C39)*24-E39 -> 0 | G39: =+IF(C39>0.333333333333333,+(C39-0.333333333333333)*24*60,"0") -> 0
A40: TOTAL DIAS TRABAJADOS | C40: =+COUNT(C10:C39) -> 13
A41: TOTAL HORAS TRABAJADAS | C41: =SUM(F10:F39) -> 119.6
A42: ATRASOS | C42: =SUM(G10:G39) -> 374

Sheet 10
A2: PLANILLA CONTROL DE ASISTENCIA
A4: ITEM | B4: 10
A5: NOMBRE | B5: DAVID ARIEL PEREDO MIRANDA
A6: CARGO | B6: Supervisor Elt/Mec Regional
A7: HABER BASICO | B7: 16240 | C7: Bs.
A9: FECHA | B9: DIA | C9: HORA INGRESO | D9: HORA SALIDA | E9: REFRIGERIO | F9: HORAS TRABAJO | G9: ATRASOS MINUTOS | H9: OBSERVACIONES
A10: 46113 | B10: =+A10 -> 46113 | C10: 0.33333333 | D10: 0.70833333 | E10: 1 | F10: =+(D10-C10)*24-E10 -> 8 | G10: =+IF(C10>0.333333333333333,+(C10-0.333333333333333)*24*60,"0") -> 0
A11: 46114 | B11: =+A11 -> 46114 | C11: 0.33333333 | D11: 0.70833333 | E11: 1 | F11: =+(D11-C11)*24-E11 -> 8 | G11: =+IF(C11>0.333333333333333,+(C11-0.333333333333333)*24*60,"0") -> 0
A12: 46115 | B12: =+A12 -> 46115 | F12: =+(D12-C12)*24-E12 -> 0 | G12: =+IF(C12>0.333333333333333,+(C12-0.333333333333333)*24*60,"0") -> 0 | H12: Feriado: Semana Santa
A13: 46116 | B13: =+A13 -> 46116 | F13: =+(D13-C13)*24-E13 -> 0 | G13: =+IF(C13>0.333333333333333,+(C13-0.333333333333333)*24*60,"0") -> 0
A14: 46117 | B14: =+A14 -> 46117 | F14: =+(D14-C14)*24-E14 -> 0 | G14: =+IF(C14>0.333333333333333,+(C14-0.333333333333333)*24*60,"0") -> 0
A15: 46118 | B15: =+A15 -> 46118 | C15: 0.33333333 | D15: 0.70833333 | E15: 1 | F15: =+(D15-C15)*24-E15 -> 8 | G15: =+IF(C15>0.333333333333333,+(C15-0.333333333333333)*24*60,"0") -> 0
A16: 46119 | B16: =+A16 -> 46119 | C16: 0.33333333 | D16: 0.70833333 | E16: 1 | F16: =+(D16-C16)*24-E16 -> 8 | G16: =+IF(C16>0.333333333333333,+(C16-0.333333333333333)*24*60,"0") -> 0
A17: 46120 | B17: =+A17 -> 46120 | C17: 0.33333333 | D17: 0.70833333 | E17: 1 | F17: =+(D17-C17)*24-E17 -> 8 | G17: =+IF(C17>0.333333333333333,+(C17-0.333333333333333)*24*60,"0") -> 0
A18: 46121 | B18: =+A18 -> 46121 | C18: 0.41041667 | D18: 0.74166667 | E18: 1 | F18: =+(D18-C18)*24-E18 -> 6.95 | G18: =+IF(C18>0.333333333333333,+(C18-0.333333333333333)*24*60,"0") -> 111
A19: 46122 | B19: =+A19 -> 46122 | C19: 0.33819444 | D19: 0.73055556 | E19: 1 | F19: =+(D19-C19)*24-E19 -> 8.4166667 | G19: =+IF(C19>0.333333333333333,+(C19-0.333333333333333)*24*60,"0") -> 7
A20: 46123 | B20: =+A20 -> 46123 | F20: =+(D20-C20)*24-E20 -> 0 | G20: =+IF(C20>0.333333333333333,+(C20-0.333333333333333)*24*60,"0") -> 0
A21: 46124 | B21: =+A21 -> 46124 | F21: =+(D21-C21)*24-E21 -> 0 | G21: =+IF(C21>0.333333333333333,+(C21-0.333333333333333)*24*60,"0") -> 0
A22: 46125 | B22: =+A22 -> 46125 | C22: 0.33958333 | D22: 0.72986111 | E22: 1 | F22: =+(D22-C22)*24-E22 -> 8.3666667 | G22: =+IF(C22>0.333333333333333,+(C22-0.333333333333333)*24*60,"0") -> 9
A23: 46126 | B23: =+A23 -> 46126 | C23: 0.33611111 | D23: 0.76597222 | E23: 1 | F23: =+(D23-C23)*24-E23 -> 9.3166667 | G23: =+IF(C23>0.333333333333333,+(C23-0.333333333333333)*24*60,"0") -> 4
A24: 46127 | B24: =+A24 -> 46127 | C24: 0.33958333 | D24: 0.75625 | E24: 1 | F24: =+(D24-C24)*24-E24 -> 9 | G24: =+IF(C24>0.333333333333333,+(C24-0.333333333333333)*24*60,"0") -> 9
A25: 46128 | B25: =+A25 -> 46128 | C25: 0.33680556 | D25: 0.73541667 | E25: 1 | F25: =+(D25-C25)*24-E25 -> 8.5666667 | G25: =+IF(C25>0.333333333333333,+(C25-0.333333333333333)*24*60,"0") -> 5
A26: 46129 | B26: =+A26 -> 46129 | C26: 0.34791667 | D26: 0.75138889 | E26: 1 | F26: =+(D26-C26)*24-E26 -> 8.6833333 | G26: =+IF(C26>0.333333333333333,+(C26-0.333333333333333)*24*60,"0") -> 21
A27: 46130 | B27: =+A27 -> 46130 | F27: =+(D27-C27)*24-E27 -> 0 | G27: =+IF(C27>0.333333333333333,+(C27-0.333333333333333)*24*60,"0") -> 0
A28: 46131 | B28: =+A28 -> 46131 | F28: =+(D28-C28)*24-E28 -> 0 | G28: =+IF(C28>0.333333333333333,+(C28-0.333333333333333)*24*60,"0") -> 0
A29: 46132 | B29: =+A29 -> 46132 | C29: 0.33541667 | D29: 0.76597222 | E29: 1 | F29: =+(D29-C29)*24-E29 -> 9.3333333 | G29: =+IF(C29>0.333333333333333,+(C29-0.333333333333333)*24*60,"0") -> 3
A30: 46133 | B30: =+A30 -> 46133 | F30: =+(D30-C30)*24-E30 -> 0 | G30: =+IF(C30>0.333333333333333,+(C30-0.333333333333333)*24*60,"0") -> 0
A31: 46134 | B31: =+A31 -> 46134 | F31: =+(D31-C31)*24-E31 -> 0 | G31: =+IF(C31>0.333333333333333,+(C31-0.333333333333333)*24*60,"0") -> 0
A32: 46135 | B32: =+A32 -> 46135 | F32: =+(D32-C32)*24-E32 -> 0 | G32: =+IF(C32>0.333333333333333,+(C32-0.333333333333333)*24*60,"0") -> 0
A33: 46136 | B33: =+A33 -> 46136 | F33: =+(D33-C33)*24-E33 -> 0 | G33: =+IF(C33>0.333333333333333,+(C33-0.333333333333333)*24*60,"0") -> 0
A34: 46137 | B34: =+A34 -> 46137 | F34: =+(D34-C34)*24-E34 -> 0 | G34: =+IF(C34>0.333333333333333,+(C34-0.333333333333333)*24*60,"0") -> 0
A35: 46138 | B35: =+A35 -> 46138 | F35: =+(D35-C35)*24-E35 -> 0 | G35: =+IF(C35>0.333333333333333,+(C35-0.333333333333333)*24*60,"0") -> 0
A36: 46139 | B36: =+A36 -> 46139 | F36: =+(D36-C36)*24-E36 -> 0 | G36: =+IF(C36>0.333333333333333,+(C36-0.333333333333333)*24*60,"0") -> 0
A37: 46140 | B37: =+A37 -> 46140 | F37: =+(D37-C37)*24-E37 -> 0 | G37: =+IF(C37>0.333333333333333,+(C37-0.333333333333333)*24*60,"0") -> 0
A38: 46141 | B38: =+A38 -> 46141 | F38: =+(D38-C38)*24-E38 -> 0 | G38: =+IF(C38>0.333333333333333,+(C38-0.333333333333333)*24*60,"0") -> 0
A39: 46142 | B39: =+A39 -> 46142 | F39: =+(D39-C39)*24-E39 -> 0 | G39: =+IF(C39>0.333333333333333,+(C39-0.333333333333333)*24*60,"0") -> 0
A40: TOTAL DIAS TRABAJADOS | C40: =+COUNT(C10:C39) -> 13
A41: TOTAL HORAS TRABAJADAS | C41: =SUM(F10:F39) -> 108.63333
A42: ATRASOS | C42: =SUM(G10:G39) -> 169

Sheet 11
A2: PLANILLA CONTROL DE ASISTENCIA
A4: ITEM | B4: 11
A5: NOMBRE | B5: ERIN CALLEJAS VELASQUEZ
A6: CARGO | B6: Supervisor Elt/Mec Regional
A7: HABER BASICO | B7: 12483 | C7: Bs.
A9: FECHA | B9: DIA | C9: HORA INGRESO | D9: HORA SALIDA | E9: REFRIGERIO | F9: HORAS TRABAJO | G9: ATRASOS MINUTOS | H9: OBSERVACIONES
A10: 46113 | B10: =+A10 -> 46113 | C10: 0.33333333 | D10: 0.70833333 | E10: 1 | F10: =+(D10-C10)*24-E10 -> 8 | G10: =+IF(C10>0.333333333333333,+(C10-0.333333333333333)*24*60,"0") -> 0
A11: 46114 | B11: =+A11 -> 46114 | F11: =+(D11-C11)*24-E11 -> 0 | G11: =+IF(C11>0.333333333333333,+(C11-0.333333333333333)*24*60,"0") -> 0 | H11: Licencia
A12: 46115 | B12: =+A12 -> 46115 | F12: =+(D12-C12)*24-E12 -> 0 | G12: =+IF(C12>0.333333333333333,+(C12-0.333333333333333)*24*60,"0") -> 0 | H12: Feriado: Semana Santa
A13: 46116 | B13: =+A13 -> 46116 | F13: =+(D13-C13)*24-E13 -> 0 | G13: =+IF(C13>0.333333333333333,+(C13-0.333333333333333)*24*60,"0") -> 0
A14: 46117 | B14: =+A14 -> 46117 | F14: =+(D14-C14)*24-E14 -> 0 | G14: =+IF(C14>0.333333333333333,+(C14-0.333333333333333)*24*60,"0") -> 0
A15: 46118 | B15: =+A15 -> 46118 | C15: 0.33333333 | D15: 0.70833333 | E15: 1 | F15: =+(D15-C15)*24-E15 -> 8 | G15: =+IF(C15>0.333333333333333,+(C15-0.333333333333333)*24*60,"0") -> 0
A16: 46119 | B16: =+A16 -> 46119 | C16: 0.33333333 | D16: 0.70833333 | E16: 1 | F16: =+(D16-C16)*24-E16 -> 8 | G16: =+IF(C16>0.333333333333333,+(C16-0.333333333333333)*24*60,"0") -> 0
A17: 46120 | B17: =+A17 -> 46120 | C17: 0.33333333 | D17: 0.70833333 | E17: 1 | F17: =+(D17-C17)*24-E17 -> 8 | G17: =+IF(C17>0.333333333333333,+(C17-0.333333333333333)*24*60,"0") -> 0
A18: 46121 | B18: =+A18 -> 46121 | C18: 0.33333333 | D18: 0.70833333 | E18: 1 | F18: =+(D18-C18)*24-E18 -> 8 | G18: =+IF(C18>0.333333333333333,+(C18-0.333333333333333)*24*60,"0") -> 0
A19: 46122 | B19: =+A19 -> 46122 | C19: 0.33333333 | D19: 0.70833333 | E19: 1 | F19: =+(D19-C19)*24-E19 -> 8 | G19: =+IF(C19>0.333333333333333,+(C19-0.333333333333333)*24*60,"0") -> 0
A20: 46123 | B20: =+A20 -> 46123 | F20: =+(D20-C20)*24-E20 -> 0 | G20: =+IF(C20>0.333333333333333,+(C20-0.333333333333333)*24*60,"0") -> 0
A21: 46124 | B21: =+A21 -> 46124 | F21: =+(D21-C21)*24-E21 -> 0 | G21: =+IF(C21>0.333333333333333,+(C21-0.333333333333333)*24*60,"0") -> 0
A22: 46125 | B22: =+A22 -> 46125 | C22: 0.33333333 | D22: 0.70833333 | E22: 1 | F22: =+(D22-C22)*24-E22 -> 8 | G22: =+IF(C22>0.333333333333333,+(C22-0.333333333333333)*24*60,"0") -> 0
A23: 46126 | B23: =+A23 -> 46126 | C23: 0.33333333 | D23: 0.75833333 | E23: 1 | F23: =+(D23-C23)*24-E23 -> 9.2 | G23: =+IF(C23>0.333333333333333,+(C23-0.333333333333333)*24*60,"0") -> 0
A24: 46127 | B24: =+A24 -> 46127 | C24: 0.34027778 | D24: 0.75902778 | E24: 1 | F24: =+(D24-C24)*24-E24 -> 9.05 | G24: =+IF(C24>0.333333333333333,+(C24-0.333333333333333)*24*60,"0") -> 10
A25: 46128 | B25: =+A25 -> 46128 | C25: 0.34791667 | D25: 0.75347222 | E25: 1 | F25: =+(D25-C25)*24-E25 -> 8.7333333 | G25: =+IF(C25>0.333333333333333,+(C25-0.333333333333333)*24*60,"0") -> 21
A26: 46129 | B26: =+A26 -> 46129 | C26: 0.34791667 | D26: 0.85 | E26: 1 | F26: =+(D26-C26)*24-E26 -> 11.05 | G26: =+IF(C26>0.333333333333333,+(C26-0.333333333333333)*24*60,"0") -> 21
A27: 46130 | B27: =+A27 -> 46130 | F27: =+(D27-C27)*24-E27 -> 0 | G27: =+IF(C27>0.333333333333333,+(C27-0.333333333333333)*24*60,"0") -> 0
A28: 46131 | B28: =+A28 -> 46131 | F28: =+(D28-C28)*24-E28 -> 0 | G28: =+IF(C28>0.333333333333333,+(C28-0.333333333333333)*24*60,"0") -> 0
A29: 46132 | B29: =+A29 -> 46132 | C29: 0.35208333 | D29: 0.725 | E29: 1 | F29: =+(D29-C29)*24-E29 -> 7.95 | G29: =+IF(C29>0.333333333333333,+(C29-0.333333333333333)*24*60,"0") -> 27
A30: 46133 | B30: =+A30 -> 46133 | F30: =+(D30-C30)*24-E30 -> 0 | G30: =+IF(C30>0.333333333333333,+(C30-0.333333333333333)*24*60,"0") -> 0
A31: 46134 | B31: =+A31 -> 46134 | F31: =+(D31-C31)*24-E31 -> 0 | G31: =+IF(C31>0.333333333333333,+(C31-0.333333333333333)*24*60,"0") -> 0
A32: 46135 | B32: =+A32 -> 46135 | F32: =+(D32-C32)*24-E32 -> 0 | G32: =+IF(C32>0.333333333333333,+(C32-0.333333333333333)*24*60,"0") -> 0
A33: 46136 | B33: =+A33 -> 46136 | F33: =+(D33-C33)*24-E33 -> 0 | G33: =+IF(C33>0.333333333333333,+(C33-0.333333333333333)*24*60,"0") -> 0
A34: 46137 | B34: =+A34 -> 46137 | F34: =+(D34-C34)*24-E34 -> 0 | G34: =+IF(C34>0.333333333333333,+(C34-0.333333333333333)*24*60,"0") -> 0
A35: 46138 | B35: =+A35 -> 46138 | F35: =+(D35-C35)*24-E35 -> 0 | G35: =+IF(C35>0.333333333333333,+(C35-0.333333333333333)*24*60,"0") -> 0
A36: 46139 | B36: =+A36 -> 46139 | F36: =+(D36-C36)*24-E36 -> 0 | G36: =+IF(C36>0.333333333333333,+(C36-0.333333333333333)*24*60,"0") -> 0
A37: 46140 | B37: =+A37 -> 46140 | F37: =+(D37-C37)*24-E37 -> 0 | G37: =+IF(C37>0.333333333333333,+(C37-0.333333333333333)*24*60,"0") -> 0
A38: 46141 | B38: =+A38 -> 46141 | F38: =+(D38-C38)*24-E38 -> 0 | G38: =+IF(C38>0.333333333333333,+(C38-0.333333333333333)*24*60,"0") -> 0
A39: 46142 | B39: =+A39 -> 46142 | F39: =+(D39-C39)*24-E39 -> 0 | G39: =+IF(C39>0.333333333333333,+(C39-0.333333333333333)*24*60,"0") -> 0
A40: TOTAL DIAS TRABAJADOS | C40: =+COUNT(C10:C39) -> 12
A41: TOTAL HORAS TRABAJADAS | C41: =SUM(F10:F39) -> 101.98333
A42: ATRASOS | C42: =SUM(G10:G39) -> 79

Sheet 12
A2: PLANILLA CONTROL DE ASISTENCIA
A4: ITEM | B4: 12
A5: NOMBRE | B5: JOSUÉ CONRRADO FERNÁNDEZ SOTEZ
A6: CARGO | B6: Encargado de Almacén
A7: HABER BASICO | B7: 3808
A9: FECHA | B9: DIA | C9: HORA INGRESO | D9: HORA SALIDA | E9: REFRIGERIO | F9: HORAS TRABAJO | G9: ATRASOS MINUTOS | H9: OBSERVACIONES
A10: 46113 | B10: =+A10 -> 46113 | C10: 0.33333333 | D10: 0.70833333 | E10: 1 | F10: =+(D10-C10)*24-E10 -> 8 | G10: =+IF(C10>0.333333333333333,+(C10-0.333333333333333)*24*60,"0") -> 0
A11: 46114 | B11: =+A11 -> 46114 | C11: 0.33333333 | D11: 0.70833333 | E11: 1 | F11: =+(D11-C11)*24-E11 -> 8 | G11: =+IF(C11>0.333333333333333,+(C11-0.333333333333333)*24*60,"0") -> 0
A12: 46115 | B12: =+A12 -> 46115 | F12: =+(D12-C12)*24-E12 -> 0 | G12: =+IF(C12>0.333333333333333,+(C12-0.333333333333333)*24*60,"0") -> 0 | H12: Feriado: Semana Santa
A13: 46116 | B13: =+A13 -> 46116 | F13: =+(D13-C13)*24-E13 -> 0 | G13: =+IF(C13>0.333333333333333,+(C13-0.333333333333333)*24*60,"0") -> 0
A14: 46117 | B14: =+A14 -> 46117 | F14: =+(D14-C14)*24-E14 -> 0 | G14: =+IF(C14>0.333333333333333,+(C14-0.333333333333333)*24*60,"0") -> 0
A15: 46118 | B15: =+A15 -> 46118 | C15: 0.33333333 | D15: 0.70833333 | E15: 1 | F15: =+(D15-C15)*24-E15 -> 8 | G15: =+IF(C15>0.333333333333333,+(C15-0.333333333333333)*24*60,"0") -> 0
A16: 46119 | B16: =+A16 -> 46119 | C16: 0.33333333 | D16: 0.70833333 | E16: 1 | F16: =+(D16-C16)*24-E16 -> 8 | G16: =+IF(C16>0.333333333333333,+(C16-0.333333333333333)*24*60,"0") -> 0
A17: 46120 | B17: =+A17 -> 46120 | C17: 0.32916667 | D17: 0.71944444 | E17: 1 | F17: =+(D17-C17)*24-E17 -> 8.3666667 | G17: =+IF(C17>0.333333333333333,+(C17-0.333333333333333)*24*60,"0") -> 0
A18: 46121 | B18: =+A18 -> 46121 | C18: 0.27430556 | D18: 0.64166667 | E18: 1 | F18: =+(D18-C18)*24-E18 -> 7.8166667 | G18: =+IF(C18>0.333333333333333,+(C18-0.333333333333333)*24*60,"0") -> 0
A19: 46122 | B19: =+A19 -> 46122 | C19: 0.32083333 | D19: 0.72013889 | E19: 1 | F19: =+(D19-C19)*24-E19 -> 8.5833333 | G19: =+IF(C19>0.333333333333333,+(C19-0.333333333333333)*24*60,"0") -> 0
A20: 46123 | B20: =+A20 -> 46123 | C20: 0.33819444 | D20: 0.50486111 | E20: 1 | F20: =+(D20-C20)*24-E20 -> 3 | G20: =+IF(C20>0.333333333333333,+(C20-0.333333333333333)*24*60,"0") -> 7
A21: 46124 | B21: =+A21 -> 46124 | F21: =+(D21-C21)*24-E21 -> 0 | G21: =+IF(C21>0.333333333333333,+(C21-0.333333333333333)*24*60,"0") -> 0
A22: 46125 | B22: =+A22 -> 46125 | C22: 0.33333333 | D22: 0.72152778 | E22: 1 | F22: =+(D22-C22)*24-E22 -> 8.3166667 | G22: =+IF(C22>0.333333333333333,+(C22-0.333333333333333)*24*60,"0") -> 0
A23: 46126 | B23: =+A23 -> 46126 | C23: 0.32152778 | D23: 0.72152778 | E23: 1 | F23: =+(D23-C23)*24-E23 -> 8.6 | G23: =+IF(C23>0.333333333333333,+(C23-0.333333333333333)*24*60,"0") -> 0
A24: 46127 | B24: =+A24 -> 46127 | C24: 0.31805556 | D24: 0.71388889 | E24: 1 | F24: =+(D24-C24)*24-E24 -> 8.5 | G24: =+IF(C24>0.333333333333333,+(C24-0.333333333333333)*24*60,"0") -> 0
A25: 46128 | B25: =+A25 -> 46128 | C25: 0.30138889 | D25: 0.64027778 | E25: 1 | F25: =+(D25-C25)*24-E25 -> 7.1333333 | G25: =+IF(C25>0.333333333333333,+(C25-0.333333333333333)*24*60,"0") -> 0
A26: 46129 | B26: =+A26 -> 46129 | C26: 0.34513889 | D26: 0.72013889 | E26: 1 | F26: =+(D26-C26)*24-E26 -> 8 | G26: =+IF(C26>0.333333333333333,+(C26-0.333333333333333)*24*60,"0") -> 17
A27: 46130 | B27: =+A27 -> 46130 | C27: 0.33125 | D27: 0.50416667 | E27: 1 | F27: =+(D27-C27)*24-E27 -> 3.15 | G27: =+IF(C27>0.333333333333333,+(C27-0.333333333333333)*24*60,"0") -> 0
A28: 46131 | B28: =+A28 -> 46131 | F28: =+(D28-C28)*24-E28 -> 0 | G28: =+IF(C28>0.333333333333333,+(C28-0.333333333333333)*24*60,"0") -> 0
A29: 46132 | B29: =+A29 -> 46132 | C29: 0.32013889 | D29: 0.72152778 | E29: 1 | F29: =+(D29-C29)*24-E29 -> 8.6333333 | G29: =+IF(C29>0.333333333333333,+(C29-0.333333333333333)*24*60,"0") -> 0
A30: 46133 | B30: =+A30 -> 46133 | F30: =+(D30-C30)*24-E30 -> 0 | G30: =+IF(C30>0.333333333333333,+(C30-0.333333333333333)*24*60,"0") -> 0
A31: 46134 | B31: =+A31 -> 46134 | F31: =+(D31-C31)*24-E31 -> 0 | G31: =+IF(C31>0.333333333333333,+(C31-0.333333333333333)*24*60,"0") -> 0
A32: 46135 | B32: =+A32 -> 46135 | F32: =+(D32-C32)*24-E32 -> 0 | G32: =+IF(C32>0.333333333333333,+(C32-0.333333333333333)*24*60,"0") -> 0
A33: 46136 | B33: =+A33 -> 46136 | F33: =+(D33-C33)*24-E33 -> 0 | G33: =+IF(C33>0.333333333333333,+(C33-0.333333333333333)*24*60,"0") -> 0
A34: 46137 | B34: =+A34 -> 46137 | F34: =+(D34-C34)*24-E34 -> 0 | G34: =+IF(C34>0.333333333333333,+(C34-0.333333333333333)*24*60,"0") -> 0
A35: 46138 | B35: =+A35 -> 46138 | F35: =+(D35-C35)*24-E35 -> 0 | G35: =+IF(C35>0.333333333333333,+(C35-0.333333333333333)*24*60,"0") -> 0
A36: 46139 | B36: =+A36 -> 46139 | F36: =+(D36-C36)*24-E36 -> 0 | G36: =+IF(C36>0.333333333333333,+(C36-0.333333333333333)*24*60,"0") -> 0
A37: 46140 | B37: =+A37 -> 46140 | F37: =+(D37-C37)*24-E37 -> 0 | G37: =+IF(C37>0.333333333333333,+(C37-0.333333333333333)*24*60,"0") -> 0
A38: 46141 | B38: =+A38 -> 46141 | F38: =+(D38-C38)*24-E38 -> 0 | G38: =+IF(C38>0.333333333333333,+(C38-0.333333333333333)*24*60,"0") -> 0
A39: 46142 | B39: =+A39 -> 46142 | F39: =+(D39-C39)*24-E39 -> 0 | G39: =+IF(C39>0.333333333333333,+(C39-0.333333333333333)*24*60,"0") -> 0
A40: TOTAL DIAS TRABAJADOS | C40: =+COUNT(C10:C39) -> 15
A41: TOTAL HORAS TRABAJADAS | C41: =SUM(F10:F39) -> 112.1
A42: ATRASOS | C42: =SUM(G10:G39) -> 24
